Workbook

Sheet 控制台
A1: 财务管理工作簿
A2: 选择公司和月份后点击刷新；金额默认人民币元。
A4: 公司编号
A5: 月份
A6: 数据状态 | B6: =IF(OR(B4="",B5=""),"请填写公司编号和月份",IF(AND(B4='刷新信息'!B6,B5='刷新信息'!B8),"当前选择与数据一致","选择已变化，请刷新"))
A7: 刷新结果 | B7: 尚未读取数据
A8: 最近刷新（UTC）
A11: 工作表 | B11: 用途
A12: 经营统计 | B12: 利润、现金收支、月度趋势
A13: 预算输入 / 预算对比 | B13: 按公司、月份、利润项目录入预算
A14: 账龄输入 / 账龄统计 | B14: 补充未核销单据；余额差额单列
A15: 出纳账 | B15: 总账现金及银行凭证明细
A16: 刷新信息 | B16: 数据身份、更新时间及原系统校验字段
A17: 使用说明 | B17: 一次性安装与口径说明
A20: 首次使用：在 Windows 运行安装脚本生成带刷新按钮的 .xlsm 文件。
A22: 黄色区域为人工输入；刷新不会覆盖预算和账龄输入。

Sheet 经营统计
A1: 经营统计
A2: 仅在选择与已刷新数据一致时显示；收支采用总账口径。
A4: 指标 | B4: 金额（元）
A5: 营业收入 | B5: =IF(AND('控制台'!B4<>"",'控制台'!B5<>"",'控制台'!B4='刷新信息'!B6,'控制台'!B5='刷新信息'!B8),SUMIFS('利润表'!C5:C200,'利润表'!F5:F200,"营业收入"),"")
A6: 营业成本 | B6: =IF(AND('控制台'!B4<>"",'控制台'!B5<>"",'控制台'!B4='刷新信息'!B6,'控制台'!B5='刷新信息'!B8),SUMIFS('利润表'!C5:C200,'利润表'!F5:F200,"营业成本"),"")
A7: 净利润 | B7: =IF(AND('控制台'!B4<>"",'控制台'!B5<>"",'控制台'!B4='刷新信息'!B6,'控制台'!B5='刷新信息'!B8),SUMIFS('利润表'!C5:C200,'利润表'!F5:F200,"净利润"),"")
A8: 现金银行流入 | B8: =IF(AND('控制台'!B4<>"",'控制台'!B5<>"",'控制台'!B4='刷新信息'!B6,'控制台'!B5='刷新信息'!B8),SUMIFS('出纳账'!I5:I6000,'出纳账'!M5:M6000,"<>内部划转"),"")
A9: 现金银行流出 | B9: =IF(AND('控制台'!B4<>"",'控制台'!B5<>"",'控制台'!B4='刷新信息'!B6,'控制台'!B5='刷新信息'!B8),SUMIFS('出纳账'!J5:J6000,'出纳账'!M5:M6000,"<>内部划转"),"")
A10: 现金银行净流入 | B10: =IF(AND('控制台'!B4<>"",'控制台'!B5<>"",'控制台'!B4='刷新信息'!B6,'控制台'!B5='刷新信息'!B8),B8-B9,"")
A11: 应收账款净额 | B11: =IF(AND('控制台'!B4<>"",'控制台'!B5<>"",'控制台'!B4='刷新信息'!B6,'控制台'!B5='刷新信息'!B8),SUMIFS('往来余额'!I5:I6000,'往来余额'!A5:A6000,"应收")-SUMIFS('往来余额'!J5:J6000,'往来余额'!A5:A6000,"应收"),"")
A12: 应付账款净额 | B12: =IF(AND('控制台'!B4<>"",'控制台'!B5<>"",'控制台'!B4='刷新信息'!B6,'控制台'!B5='刷新信息'!B8),SUMIFS('往来余额'!J5:J6000,'往来余额'!A5:A6000,"应付")-SUMIFS('往来余额'!I5:I6000,'往来余额'!A5:A6000,"应付"),"")
A15: 月份 | B15: 营业收入 | C15: 营业成本 | D15: 净利润
A16: =IF('控制台'!B5="","",LEFT('控制台'!B5,4)&"-01") | B16: =IF(AND(AND('控制台'!B4<>"",'控制台'!B5<>"",'控制台'!B4='刷新信息'!B6,'控制台'!B5='刷新信息'!B8),COUNTIF('月度趋势'!A5:A1000,A16)>0),SUMIFS('月度趋势'!D5:D1000,'月度趋势'!A5:A1000,A16,'月度趋势'!E5:E1000,"营业收入"),"") | C16: =IF(AND(AND('控制台'!B4<>"",'控制台'!B5<>"",'控制台'!B4='刷新信息'!B6,'控制台'!B5='刷新信息'!B8),COUNTIF('月度趋势'!A5:A1000,A16)>0),SUMIFS('月度趋势'!D5:D1000,'月度趋势'!A5:A1000,A16,'月度趋势'!E5:E1000,"营业成本"),"") | D16: =IF(AND(AND('控制台'!B4<>"",'控制台'!B5<>"",'控制台'!B4='刷新信息'!B6,'控制台'!B5='刷新信息'!B8),COUNTIF('月度趋势'!A5:A1000,A16)>0),SUMIFS('月度趋势'!D5:D1000,'月度趋势'!A5:A1000,A16,'月度趋势'!E5:E1000,"净利润"),"")
A17: =IF('控制台'!B5="","",LEFT('控制台'!B5,4)&"-02") | B17: =IF(AND(AND('控制台'!B4<>"",'控制台'!B5<>"",'控制台'!B4='刷新信息'!B6,'控制台'!B5='刷新信息'!B8),COUNTIF('月度趋势'!A5:A1000,A17)>0),SUMIFS('月度趋势'!D5:D1000,'月度趋势'!A5:A1000,A17,'月度趋势'!E5:E1000,"营业收入"),"") | C17: =IF(AND(AND('控制台'!B4<>"",'控制台'!B5<>"",'控制台'!B4='刷新信息'!B6,'控制台'!B5='刷新信息'!B8),COUNTIF('月度趋势'!A5:A1000,A17)>0),SUMIFS('月度趋势'!D5:D1000,'月度趋势'!A5:A1000,A17,'月度趋势'!E5:E1000,"营业成本"),"") | D17: =IF(AND(AND('控制台'!B4<>"",'控制台'!B5<>"",'控制台'!B4='刷新信息'!B6,'控制台'!B5='刷新信息'!B8),COUNTIF('月度趋势'!A5:A1000,A17)>0),SUMIFS('月度趋势'!D5:D1000,'月度趋势'!A5:A1000,A17,'月度趋势'!E5:E1000,"净利润"),"")
A18: =IF('控制台'!B5="","",LEFT('控制台'!B5,4)&"-03") | B18: =IF(AND(AND('控制台'!B4<>"",'控制台'!B5<>"",'控制台'!B4='刷新信息'!B6,'控制台'!B5='刷新信息'!B8),COUNTIF('月度趋势'!A5:A1000,A18)>0),SUMIFS('月度趋势'!D5:D1000,'月度趋势'!A5:A1000,A18,'月度趋势'!E5:E1000,"营业收入"),"") | C18: =IF(AND(AND('控制台'!B4<>"",'控制台'!B5<>"",'控制台'!B4='刷新信息'!B6,'控制台'!B5='刷新信息'!B8),COUNTIF('月度趋势'!A5:A1000,A18)>0),SUMIFS('月度趋势'!D5:D1000,'月度趋势'!A5:A1000,A18,'月度趋势'!E5:E1000,"营业成本"),"") | D18: =IF(AND(AND('控制台'!B4<>"",'控制台'!B5<>"",'控制台'!B4='刷新信息'!B6,'控制台'!B5='刷新信息'!B8),COUNTIF('月度趋势'!A5:A1000,A18)>0),SUMIFS('月度趋势'!D5:D1000,'月度趋势'!A5:A1000,A18,'月度趋势'!E5:E1000,"净利润"),"")
A19: =IF('控制台'!B5="","",LEFT('控制台'!B5,4)&"-04") | B19: =IF(AND(AND('控制台'!B4<>"",'控制台'!B5<>"",'控制台'!B4='刷新信息'!B6,'控制台'!B5='刷新信息'!B8),COUNTIF('月度趋势'!A5:A1000,A19)>0),SUMIFS('月度趋势'!D5:D1000,'月度趋势'!A5:A1000,A19,'月度趋势'!E5:E1000,"营业收入"),"") | C19: =IF(AND(AND('控制台'!B4<>"",'控制台'!B5<>"",'控制台'!B4='刷新信息'!B6,'控制台'!B5='刷新信息'!B8),COUNTIF('月度趋势'!A5:A1000,A19)>0),SUMIFS('月度趋势'!D5:D1000,'月度趋势'!A5:A1000,A19,'月度趋势'!E5:E1000,"营业成本"),"") | D19: =IF(AND(AND('控制台'!B4<>"",'控制台'!B5<>"",'控制台'!B4='刷新信息'!B6,'控制台'!B5='刷新信息'!B8),COUNTIF('月度趋势'!A5:A1000,A19)>0),SUMIFS('月度趋势'!D5:D1000,'月度趋势'!A5:A1000,A19,'月度趋势'!E5:E1000,"净利润"),"")
A20: =IF('控制台'!B5="","",LEFT('控制台'!B5,4)&"-05") | B20: =IF(AND(AND('控制台'!B4<>"",'控制台'!B5<>"",'控制台'!B4='刷新信息'!B6,'控制台'!B5='刷新信息'!B8),COUNTIF('月度趋势'!A5:A1000,A20)>0),SUMIFS('月度趋势'!D5:D1000,'月度趋势'!A5:A1000,A20,'月度趋势'!E5:E1000,"营业收入"),"") | C20: =IF(AND(AND('控制台'!B4<>"",'控制台'!B5<>"",'控制台'!B4='刷新信息'!B6,'控制台'!B5='刷新信息'!B8),COUNTIF('月度趋势'!A5:A1000,A20)>0),SUMIFS('月度趋势'!D5:D1000,'月度趋势'!A5:A1000,A20,'月度趋势'!E5:E1000,"营业成本"),"") | D20: =IF(AND(AND('控制台'!B4<>"",'控制台'!B5<>"",'控制台'!B4='刷新信息'!B6,'控制台'!B5='刷新信息'!B8),COUNTIF('月度趋势'!A5:A1000,A20)>0),SUMIFS('月度趋势'!D5:D1000,'月度趋势'!A5:A1000,A20,'月度趋势'!E5:E1000,"净利润"),"")
A21: =IF('控制台'!B5="","",LEFT('控制台'!B5,4)&"-06") | B21: =IF(AND(AND('控制台'!B4<>"",'控制台'!B5<>"",'控制台'!B4='刷新信息'!B6,'控制台'!B5='刷新信息'!B8),COUNTIF('月度趋势'!A5:A1000,A21)>0),SUMIFS('月度趋势'!D5:D1000,'月度趋势'!A5:A1000,A21,'月度趋势'!E5:E1000,"营业收入"),"") | C21: =IF(AND(AND('控制台'!B4<>"",'控制台'!B5<>"",'控制台'!B4='刷新信息'!B6,'控制台'!B5='刷新信息'!B8),COUNTIF('月度趋势'!A5:A1000,A21)>0),SUMIFS('月度趋势'!D5:D1000,'月度趋势'!A5:A1000,A21,'月度趋势'!E5:E1000,"营业成本"),"") | D21: =IF(AND(AND('控制台'!B4<>"",'控制台'!B5<>"",'控制台'!B4='刷新信息'!B6,'控制台'!B5='刷新信息'!B8),COUNTIF('月度趋势'!A5:A1000,A21)>0),SUMIFS('月度趋势'!D5:D1000,'月度趋势'!A5:A1000,A21,'月度趋势'!E5:E1000,"净利润"),"")
A22: =IF('控制台'!B5="","",LEFT('控制台'!B5,4)&"-07") | B22: =IF(AND(AND('控制台'!B4<>"",'控制台'!B5<>"",'控制台'!B4='刷新信息'!B6,'控制台'!B5='刷新信息'!B8),COUNTIF('月度趋势'!A5:A1000,A22)>0),SUMIFS('月度趋势'!D5:D1000,'月度趋势'!A5:A1000,A22,'月度趋势'!E5:E1000,"营业收入"),"") | C22: =IF(AND(AND('控制台'!B4<>"",'控制台'!B5<>"",'控制台'!B4='刷新信息'!B6,'控制台'!B5='刷新信息'!B8),COUNTIF('月度趋势'!A5:A1000,A22)>0),SUMIFS('月度趋势'!D5:D1000,'月度趋势'!A5:A1000,A22,'月度趋势'!E5:E1000,"营业成本"),"") | D22: =IF(AND(AND('控制台'!B4<>"",'控制台'!B5<>"",'控制台'!B4='刷新信息'!B6,'控制台'!B5='刷新信息'!B8),COUNTIF('月度趋势'!A5:A1000,A22)>0),SUMIFS('月度趋势'!D5:D1000,'月度趋势'!A5:A1000,A22,'月度趋势'!E5:E1000,"净利润"),"")
A23: =IF('控制台'!B5="","",LEFT('控制台'!B5,4)&"-08") | B23: =IF(AND(AND('控制台'!B4<>"",'控制台'!B5<>"",'控制台'!B4='刷新信息'!B6,'控制台'!B5='刷新信息'!B8),COUNTIF('月度趋势'!A5:A1000,A23)>0),SUMIFS('月度趋势'!D5:D1000,'月度趋势'!A5:A1000,A23,'月度趋势'!E5:E1000,"营业收入"),"") | C23: =IF(AND(AND('控制台'!B4<>"",'控制台'!B5<>"",'控制台'!B4='刷新信息'!B6,'控制台'!B5='刷新信息'!B8),COUNTIF('月度趋势'!A5:A1000,A23)>0),SUMIFS('月度趋势'!D5:D1000,'月度趋势'!A5:A1000,A23,'月度趋势'!E5:E1000,"营业成本"),"") | D23: =IF(AND(AND('控制台'!B4<>"",'控制台'!B5<>"",'控制台'!B4='刷新信息'!B6,'控制台'!B5='刷新信息'!B8),COUNTIF('月度趋势'!A5:A1000,A23)>0),SUMIFS('月度趋势'!D5:D1000,'月度趋势'!A5:A1000,A23,'月度趋势'!E5:E1000,"净利润"),"")
A24: =IF('控制台'!B5="","",LEFT('控制台'!B5,4)&"-09") | B24: =IF(AND(AND('控制台'!B4<>"",'控制台'!B5<>"",'控制台'!B4='刷新信息'!B6,'控制台'!B5='刷新信息'!B8),COUNTIF('月度趋势'!A5:A1000,A24)>0),SUMIFS('月度趋势'!D5:D1000,'月度趋势'!A5:A1000,A24,'月度趋势'!E5:E1000,"营业收入"),"") | C24: =IF(AND(AND('控制台'!B4<>"",'控制台'!B5<>"",'控制台'!B4='刷新信息'!B6,'控制台'!B5='刷新信息'!B8),COUNTIF('月度趋势'!A5:A1000,A24)>0),SUMIFS('月度趋势'!D5:D1000,'月度趋势'!A5:A1000,A24,'月度趋势'!E5:E1000,"营业成本"),"") | D24: =IF(AND(AND('控制台'!B4<>"",'控制台'!B5<>"",'控制台'!B4='刷新信息'!B6,'控制台'!B5='刷新信息'!B8),COUNTIF('月度趋势'!A5:A1000,A24)>0),SUMIFS('月度趋势'!D5:D1000,'月度趋势'!A5:A1000,A24,'月度趋势'!E5:E1000,"净利润"),"")
A25: =IF('控制台'!B5="","",LEFT('控制台'!B5,4)&"-10") | B25: =IF(AND(AND('控制台'!B4<>"",'控制台'!B5<>"",'控制台'!B4='刷新信息'!B6,'控制台'!B5='刷新信息'!B8),COUNTIF('月度趋势'!A5:A1000,A25)>0),SUMIFS('月度趋势'!D5:D1000,'月度趋势'!A5:A1000,A25,'月度趋势'!E5:E1000,"营业收入"),"") | C25: =IF(AND(AND('控制台'!B4<>"",'控制台'!B5<>"",'控制台'!B4='刷新信息'!B6,'控制台'!B5='刷新信息'!B8),COUNTIF('月度趋势'!A5:A1000,A25)>0),SUMIFS('月度趋势'!D5:D1000,'月度趋势'!A5:A1000,A25,'月度趋势'!E5:E1000,"营业成本"),"") | D25: =IF(AND(AND('控制台'!B4<>"",'控制台'!B5<>"",'控制台'!B4='刷新信息'!B6,'控制台'!B5='刷新信息'!B8),COUNTIF('月度趋势'!A5:A1000,A25)>0),SUMIFS('月度趋势'!D5:D1000,'月度趋势'!A5:A1000,A25,'月度趋势'!E5:E1000,"净利润"),"")
A26: =IF('控制台'!B5="","",LEFT('控制台'!B5,4)&"-11") | B26: =IF(AND(AND('控制台'!B4<>"",'控制台'!B5<>"",'控制台'!B4='刷新信息'!B6,'控制台'!B5='刷新信息'!B8),COUNTIF('月度趋势'!A5:A1000,A26)>0),SUMIFS('月度趋势'!D5:D1000,'月度趋势'!A5:A1000,A26,'月度趋势'!E5:E1000,"营业收入"),"") | C26: =IF(AND(AND('控制台'!B4<>"",'控制台'!B5<>"",'控制台'!B4='刷新信息'!B6,'控制台'!B5='刷新信息'!B8),COUNTIF('月度趋势'!A5:A1000,A26)>0),SUMIFS('月度趋势'!D5:D1000,'月度趋势'!A5:A1000,A26,'月度趋势'!E5:E1000,"营业成本"),"") | D26: =IF(AND(AND('控制台'!B4<>"",'控制台'!B5<>"",'控制台'!B4='刷新信息'!B6,'控制台'!B5='刷新信息'!B8),COUNTIF('月度趋势'!A5:A1000,A26)>0),SUMIFS('月度趋势'!D5:D1000,'月度趋势'!A5:A1000,A26,'月度趋势'!E5:E1000,"净利润"),"")
A27: =IF('控制台'!B5="","",LEFT('控制台'!B5,4)&"-12") | B27: =IF(AND(AND('控制台'!B4<>"",'控制台'!B5<>"",'控制台'!B4='刷新信息'!B6,'控制台'!B5='刷新信息'!B8),COUNTIF('月度趋势'!A5:A1000,A27)>0),SUMIFS('月度趋势'!D5:D1000,'月度趋势'!A5:A1000,A27,'月度趋势'!E5:E1000,"营业收入"),"") | C27: =IF(AND(AND('控制台'!B4<>"",'控制台'!B5<>"",'控制台'!B4='刷新信息'!B6,'控制台'!B5='刷新信息'!B8),COUNTIF('月度趋势'!A5:A1000,A27)>0),SUMIFS('月度趋势'!D5:D1000,'月度趋势'!A5:A1000,A27,'月度趋势'!E5:E1000,"营业成本"),"") | D27: =IF(AND(AND('控制台'!B4<>"",'控制台'!B5<>"",'控制台'!B4='刷新信息'!B6,'控制台'!B5='刷新信息'!B8),COUNTIF('月度趋势'!A5:A1000,A27)>0),SUMIFS('月度趋势'!D5:D1000,'月度趋势'!A5:A1000,A27,'月度趋势'!E5:E1000,"净利润"),"")

Sheet 预算输入
A1: 预算输入
A2: 每行对应公司、月份、利润项目编码；同一组合可分笔录入，按合计比较。
A4: 公司编号 | B4: 月份 | C4: 利润项目编码 | D4: 项目名称 | E4: 预算金额 | F4: 说明

Sheet 预算对比
A1: 预算对比
A2: 实际－预算；费用正差额表示超支。未录入预算时差额留空。
A4: 项目编码 | B4: 利润项目 | C4: 实际金额 | D4: 预算金额 | E4: 差额 | F4: 差异率
A5: =IF('利润表'!A5="","",'利润表'!A5) | B5: =IF('利润表'!B5="","",'利润表'!B5) | C5: =IF(AND(AND('控制台'!B4<>"",'控制台'!B5<>"",'控制台'!B4='刷新信息'!B6,'控制台'!B5='刷新信息'!B8),ISNUMBER('利润表'!C5)),'利润表'!C5,"") | D5: =IF(AND(AND('控制台'!B4<>"",'控制台'!B5<>"",'控制台'!B4='刷新信息'!B6,'控制台'!B5='刷新信息'!B8),COUNTIFS('预算输入'!A5:A204,'控制台'!B4,'预算输入'!B5:B204,'控制台'!B5,'预算输入'!C5:C204,A5)>0),SUMIFS('预算输入'!E5:E204,'预算输入'!A5:A204,'控制台'!B4,'预算输入'!B5:B204,'控制台'!B5,'预算输入'!C5:C204,A5),"") | E5: =IF(OR(D5="",C5=""),"",C5-D5) | F5: =IF(OR(D5="",D5=0),"",E5/ABS(D5))
A6: =IF('利润表'!A6="","",'利润表'!A6) | B6: =IF('利润表'!B6="","",'利润表'!B6) | C6: =IF(AND(AND('控制台'!B4<>"",'控制台'!B5<>"",'控制台'!B4='刷新信息'!B6,'控制台'!B5='刷新信息'!B8),ISNUMBER('利润表'!C6)),'利润表'!C6,"") | D6: =IF(AND(AND('控制台'!B4<>"",'控制台'!B5<>"",'控制台'!B4='刷新信息'!B6,'控制台'!B5='刷新信息'!B8),COUNTIFS('预算输入'!A5:A204,'控制台'!B4,'预算输入'!B5:B204,'控制台'!B5,'预算输入'!C5:C204,A6)>0),SUMIFS('预算输入'!E5:E204,'预算输入'!A5:A204,'控制台'!B4,'预算输入'!B5:B204,'控制台'!B5,'预算输入'!C5:C204,A6),"") | E6: =IF(OR(D6="",C6=""),"",C6-D6) | F6: =IF(OR(D6="",D6=0),"",E6/ABS(D6))
A7: =IF('利润表'!A7="","",'利润表'!A7) | B7: =IF('利润表'!B7="","",'利润表'!B7) | C7: =IF(AND(AND('控制台'!B4<>"",'控制台'!B5<>"",'控制台'!B4='刷新信息'!B6,'控制台'!B5='刷新信息'!B8),ISNUMBER('利润表'!C7)),'利润表'!C7,"") | D7: =IF(AND(AND('控制台'!B4<>"",'控制台'!B5<>"",'控制台'!B4='刷新信息'!B6,'控制台'!B5='刷新信息'!B8),COUNTIFS('预算输入'!A5:A204,'控制台'!B4,'预算输入'!B5:B204,'控制台'!B5,'预算输入'!C5:C204,A7)>0),SUMIFS('预算输入'!E5:E204,'预算输入'!A5:A204,'控制台'!B4,'预算输入'!B5:B204,'控制台'!B5,'预算输入'!C5:C204,A7),"") | E7: =IF(OR(D7="",C7=""),"",C7-D7) | F7: =IF(OR(D7="",D7=0),"",E7/ABS(D7))
A8: =IF('利润表'!A8="","",'利润表'!A8) | B8: =IF('利润表'!B8="","",'利润表'!B8) | C8: =IF(AND(AND('控制台'!B4<>"",'控制台'!B5<>"",'控制台'!B4='刷新信息'!B6,'控制台'!B5='刷新信息'!B8),ISNUMBER('利润表'!C8)),'利润表'!C8,"") | D8: =IF(AND(AND('控制台'!B4<>"",'控制台'!B5<>"",'控制台'!B4='刷新信息'!B6,'控制台'!B5='刷新信息'!B8),COUNTIFS('预算输入'!A5:A204,'控制台'!B4,'预算输入'!B5:B204,'控制台'!B5,'预算输入'!C5:C204,A8)>0),SUMIFS('预算输入'!E5:E204,'预算输入'!A5:A204,'控制台'!B4,'预算输入'!B5:B204,'控制台'!B5,'预算输入'!C5:C204,A8),"") | E8: =IF(OR(D8="",C8=""),"",C8-D8) | F8: =IF(OR(D8="",D8=0),"",E8/ABS(D8))
A9: =IF('利润表'!A9="","",'利润表'!A9) | B9: =IF('利润表'!B9="","",'利润表'!B9) | C9: =IF(AND(AND('控制台'!B4<>"",'控制台'!B5<>"",'控制台'!B4='刷新信息'!B6,'控制台'!B5='刷新信息'!B8),ISNUMBER('利润表'!C9)),'利润表'!C9,"") | D9: =IF(AND(AND('控制台'!B4<>"",'控制台'!B5<>"",'控制台'!B4='刷新信息'!B6,'控制台'!B5='刷新信息'!B8),COUNTIFS('预算输入'!A5:A204,'控制台'!B4,'预算输入'!B5:B204,'控制台'!B5,'预算输入'!C5:C204,A9)>0),SUMIFS('预算输入'!E5:E204,'预算输入'!A5:A204,'控制台'!B4,'预算输入'!B5:B204,'控制台'!B5,'预算输入'!C5:C204,A9),"") | E9: =IF(OR(D9="",C9=""),"",C9-D9) | F9: =IF(OR(D9="",D9=0),"",E9/ABS(D9))
A10: =IF('利润表'!A10="","",'利润表'!A10) | B10: =IF('利润表'!B10="","",'利润表'!B10) | C10: =IF(AND(AND('控制台'!B4<>"",'控制台'!B5<>"",'控制台'!B4='刷新信息'!B6,'控制台'!B5='刷新信息'!B8),ISNUMBER('利润表'!C10)),'利润表'!C10,"") | D10: =IF(AND(AND('控制台'!B4<>"",'控制台'!B5<>"",'控制台'!B4='刷新信息'!B6,'控制台'!B5='刷新信息'!B8),COUNTIFS('预算输入'!A5:A204,'控制台'!B4,'预算输入'!B5:B204,'控制台'!B5,'预算输入'!C5:C204,A10)>0),SUMIFS('预算输入'!E5:E204,'预算输入'!A5:A204,'控制台'!B4,'预算输入'!B5:B204,'控制台'!B5,'预算输入'!C5:C204,A10),"") | E10: =IF(OR(D10="",C10=""),"",C10-D10) | F10: =IF(OR(D10="",D10=0),"",E10/ABS(D10))
A11: =IF('利润表'!A11="","",'利润表'!A11) | B11: =IF('利润表'!B11="","",'利润表'!B11) | C11: =IF(AND(AND('控制台'!B4<>"",'控制台'!B5<>"",'控制台'!B4='刷新信息'!B6,'控制台'!B5='刷新信息'!B8),ISNUMBER('利润表'!C11)),'利润表'!C11,"") | D11: =IF(AND(AND('控制台'!B4<>"",'控制台'!B5<>"",'控制台'!B4='刷新信息'!B6,'控制台'!B5='刷新信息'!B8),COUNTIFS('预算输入'!A5:A204,'控制台'!B4,'预算输入'!B5:B204,'控制台'!B5,'预算输入'!C5:C204,A11)>0),SUMIFS('预算输入'!E5:E204,'预算输入'!A5:A204,'控制台'!B4,'预算输入'!B5:B204,'控制台'!B5,'预算输入'!C5:C204,A11),"") | E11: =IF(OR(D11="",C11=""),"",C11-D11) | F11: =IF(OR(D11="",D11=0),"",E11/ABS(D11))
A12: =IF('利润表'!A12="","",'利润表'!A12) | B12: =IF('利润表'!B12="","",'利润表'!B12) | C12: =IF(AND(AND('控制台'!B4<>"",'控制台'!B5<>"",'控制台'!B4='刷新信息'!B6,'控制台'!B5='刷新信息'!B8),ISNUMBER('利润表'!C12)),'利润表'!C12,"") | D12: =IF(AND(AND('控制台'!B4<>"",'控制台'!B5<>"",'控制台'!B4='刷新信息'!B6,'控制台'!B5='刷新信息'!B8),COUNTIFS('预算输入'!A5:A204,'控制台'!B4,'预算输入'!B5:B204,'控制台'!B5,'预算输入'!C5:C204,A12)>0),SUMIFS('预算输入'!E5:E204,'预算输入'!A5:A204,'控制台'!B4,'预算输入'!B5:B204,'控制台'!B5,'预算输入'!C5:C204,A12),"") | E12: =IF(OR(D12="",C12=""),"",C12-D12) | F12: =IF(OR(D12="",D12=0),"",E12/ABS(D12))
A13: =IF('利润表'!A13="","",'利润表'!A13) | B13: =IF('利润表'!B13="","",'利润表'!B13) | C13: =IF(AND(AND('控制台'!B4<>"",'控制台'!B5<>"",'控制台'!B4='刷新信息'!B6,'控制台'!B5='刷新信息'!B8),ISNUMBER('利润表'!C13)),'利润表'!C13,"") | D13: =IF(AND(AND('控制台'!B4<>"",'控制台'!B5<>"",'控制台'!B4='刷新信息'!B6,'控制台'!B5='刷新信息'!B8),COUNTIFS('预算输入'!A5:A204,'控制台'!B4,'预算输入'!B5:B204,'控制台'!B5,'预算输入'!C5:C204,A13)>0),SUMIFS('预算输入'!E5:E204,'预算输入'!A5:A204,'控制台'!B4,'预算输入'!B5:B204,'控制台'!B5,'预算输入'!C5:C204,A13),"") | E13: =IF(OR(D13="",C13=""),"",C13-D13) | F13: =IF(OR(D13="",D13=0),"",E13/ABS(D13))
A14: =IF('利润表'!A14="","",'利润表'!A14) | B14: =IF('利润表'!B14="","",'利润表'!B14) | C14: =IF(AND(AND('控制台'!B4<>"",'控制台'!B5<>"",'控制台'!B4='刷新信息'!B6,'控制台'!B5='刷新信息'!B8),ISNUMBER('利润表'!C14)),'利润表'!C14,"") | D14: =IF(AND(AND('控制台'!B4<>"",'控制台'!B5<>"",'控制台'!B4='刷新信息'!B6,'控制台'!B5='刷新信息'!B8),COUNTIFS('预算输入'!A5:A204,'控制台'!B4,'预算输入'!B5:B204,'控制台'!B5,'预算输入'!C5:C204,A14)>0),SUMIFS('预算输入'!E5:E204,'预算输入'!A5:A204,'控制台'!B4,'预算输入'!B5:B204,'控制台'!B5,'预算输入'!C5:C204,A14),"") | E14: =IF(OR(D14="",C14=""),"",C14-D14) | F14: =IF(OR(D14="",D14=0),"",E14/ABS(D14))
A15: =IF('利润表'!A15="","",'利润表'!A15) | B15: =IF('利润表'!B15="","",'利润表'!B15) | C15: =IF(AND(AND('控制台'!B4<>"",'控制台'!B5<>"",'控制台'!B4='刷新信息'!B6,'控制台'!B5='刷新信息'!B8),ISNUMBER('利润表'!C15)),'利润表'!C15,"") | D15: =IF(AND(AND('控制台'!B4<>"",'控制台'!B5<>"",'控制台'!B4='刷新信息'!B6,'控制台'!B5='刷新信息'!B8),COUNTIFS('预算输入'!A5:A204,'控制台'!B4,'预算输入'!B5:B204,'控制台'!B5,'预算输入'!C5:C204,A15)>0),SUMIFS('预算输入'!E5:E204,'预算输入'!A5:A204,'控制台'!B4,'预算输入'!B5:B204,'控制台'!B5,'预算输入'!C5:C204,A15),"") | E15: =IF(OR(D15="",C15=""),"",C15-D15) | F15: =IF(OR(D15="",D15=0),"",E15/ABS(D15))
A16: =IF('利润表'!A16="","",'利润表'!A16) | B16: =IF('利润表'!B16="","",'利润表'!B16) | C16: =IF(AND(AND('控制台'!B4<>"",'控制台'!B5<>"",'控制台'!B4='刷新信息'!B6,'控制台'!B5='刷新信息'!B8),ISNUMBER('利润表'!C16)),'利润表'!C16,"") | D16: =IF(AND(AND('控制台'!B4<>"",'控制台'!B5<>"",'控制台'!B4='刷新信息'!B6,'控制台'!B5='刷新信息'!B8),COUNTIFS('预算输入'!A5:A204,'控制台'!B4,'预算输入'!B5:B204,'控制台'!B5,'预算输入'!C5:C204,A16)>0),SUMIFS('预算输入'!E5:E204,'预算输入'!A5:A204,'控制台'!B4,'预算输入'!B5:B204,'控制台'!B5,'预算输入'!C5:C204,A16),"") | E16: =IF(OR(D16="",C16=""),"",C16-D16) | F16: =IF(OR(D16="",D16=0),"",E16/ABS(D16))
A17: =IF('利润表'!A17="","",'利润表'!A17) | B17: =IF('利润表'!B17="","",'利润表'!B17) | C17: =IF(AND(AND('控制台'!B4<>"",'控制台'!B5<>"",'控制台'!B4='刷新信息'!B6,'控制台'!B5='刷新信息'!B8),ISNUMBER('利润表'!C17)),'利润表'!C17,"") | D17: =IF(AND(AND('控制台'!B4<>"",'控制台'!B5<>"",'控制台'!B4='刷新信息'!B6,'控制台'!B5='刷新信息'!B8),COUNTIFS('预算输入'!A5:A204,'控制台'!B4,'预算输入'!B5:B204,'控制台'!B5,'预算输入'!C5:C204,A17)>0),SUMIFS('预算输入'!E5:E204,'预算输入'!A5:A204,'控制台'!B4,'预算输入'!B5:B204,'控制台'!B5,'预算输入'!C5:C204,A17),"") | E17: =IF(OR(D17="",C17=""),"",C17-D17) | F17: =IF(OR(D17="",D17=0),"",E17/ABS(D17))
A18: =IF('利润表'!A18="","",'利润表'!A18) | B18: =IF('利润表'!B18="","",'利润表'!B18) | C18: =IF(AND(AND('控制台'!B4<>"",'控制台'!B5<>"",'控制台'!B4='刷新信息'!B6,'控制台'!B5='刷新信息'!B8),ISNUMBER('利润表'!C18)),'利润表'!C18,"") | D18: =IF(AND(AND('控制台'!B4<>"",'控制台'!B5<>"",'控制台'!B4='刷新信息'!B6,'控制台'!B5='刷新信息'!B8),COUNTIFS('预算输入'!A5:A204,'控制台'!B4,'预算输入'!B5:B204,'控制台'!B5,'预算输入'!C5:C204,A18)>0),SUMIFS('预算输入'!E5:E204,'预算输入'!A5:A204,'控制台'!B4,'预算输入'!B5:B204,'控制台'!B5,'预算输入'!C5:C204,A18),"") | E18: =IF(OR(D18="",C18=""),"",C18-D18) | F18: =IF(OR(D18="",D18=0),"",E18/ABS(D18))
A19: =IF('利润表'!A19="","",'利润表'!A19) | B19: =IF('利润表'!B19="","",'利润表'!B19) | C19: =IF(AND(AND('控制台'!B4<>"",'控制台'!B5<>"",'控制台'!B4='刷新信息'!B6,'控制台'!B5='刷新信息'!B8),ISNUMBER('利润表'!C19)),'利润表'!C19,"") | D19: =IF(AND(AND('控制台'!B4<>"",'控制台'!B5<>"",'控制台'!B4='刷新信息'!B6,'控制台'!B5='刷新信息'!B8),COUNTIFS('预算输入'!A5:A204,'控制台'!B4,'预算输入'!B5:B204,'控制台'!B5,'预算输入'!C5:C204,A19)>0),SUMIFS('预算输入'!E5:E204,'预算输入'!A5:A204,'控制台'!B4,'预算输入'!B5:B204,'控制台'!B5,'预算输入'!C5:C204,A19),"") | E19: =IF(OR(D19="",C19=""),"",C19-D19) | F19: =IF(OR(D19="",D19=0),"",E19/ABS(D19))
A20: =IF('利润表'!A20="","",'利润表'!A20) | B20: =IF('利润表'!B20="","",'利润表'!B20) | C20: =IF(AND(AND('控制台'!B4<>"",'控制台'!B5<>"",'控制台'!B4='刷新信息'!B6,'控制台'!B5='刷新信息'!B8),ISNUMBER('利润表'!C20)),'利润表'!C20,"") | D20: =IF(AND(AND('控制台'!B4<>"",'控制台'!B5<>"",'控制台'!B4='刷新信息'!B6,'控制台'!B5='刷新信息'!B8),COUNTIFS('预算输入'!A5:A204,'控制台'!B4,'预算输入'!B5:B204,'控制台'!B5,'预算输入'!C5:C204,A20)>0),SUMIFS('预算输入'!E5:E204,'预算输入'!A5:A204,'控制台'!B4,'预算输入'!B5:B204,'控制台'!B5,'预算输入'!C5:C204,A20),"") | E20: =IF(OR(D20="",C20=""),"",C20-D20) | F20: =IF(OR(D20="",D20=0),"",E20/ABS(D20))
A21: =IF('利润表'!A21="","",'利润表'!A21) | B21: =IF('利润表'!B21="","",'利润表'!B21) | C21: =IF(AND(AND('控制台'!B4<>"",'控制台'!B5<>"",'控制台'!B4='刷新信息'!B6,'控制台'!B5='刷新信息'!B8),ISNUMBER('利润表'!C21)),'利润表'!C21,"") | D21: =IF(AND(AND('控制台'!B4<>"",'控制台'!B5<>"",'控制台'!B4='刷新信息'!B6,'控制台'!B5='刷新信息'!B8),COUNTIFS('预算输入'!A5:A204,'控制台'!B4,'预算输入'!B5:B204,'控制台'!B5,'预算输入'!C5:C204,A21)>0),SUMIFS('预算输入'!E5:E204,'预算输入'!A5:A204,'控制台'!B4,'预算输入'!B5:B204,'控制台'!B5,'预算输入'!C5:C204,A21),"") | E21: =IF(OR(D21="",C21=""),"",C21-D21) | F21: =IF(OR(D21="",D21=0),"",E21/ABS(D21))
A22: =IF('利润表'!A22="","",'利润表'!A22) | B22: =IF('利润表'!B22="","",'利润表'!B22) | C22: =IF(AND(AND('控制台'!B4<>"",'控制台'!B5<>"",'控制台'!B4='刷新信息'!B6,'控制台'!B5='刷新信息'!B8),ISNUMBER('利润表'!C22)),'利润表'!C22,"") | D22: =IF(AND(AND('控制台'!B4<>"",'控制台'!B5<>"",'控制台'!B4='刷新信息'!B6,'控制台'!B5='刷新信息'!B8),COUNTIFS('预算输入'!A5:A204,'控制台'!B4,'预算输入'!B5:B204,'控制台'!B5,'预算输入'!C5:C204,A22)>0),SUMIFS('预算输入'!E5:E204,'预算输入'!A5:A204,'控制台'!B4,'预算输入'!B5:B204,'控制台'!B5,'预算输入'!C5:C204,A22),"") | E22: =IF(OR(D22="",C22=""),"",C22-D22) | F22: =IF(OR(D22="",D22=0),"",E22/ABS(D22))
A23: =IF('利润表'!A23="","",'利润表'!A23) | B23: =IF('利润表'!B23="","",'利润表'!B23) | C23: =IF(AND(AND('控制台'!B4<>"",'控制台'!B5<>"",'控制台'!B4='刷新信息'!B6,'控制台'!B5='刷新信息'!B8),ISNUMBER('利润表'!C23)),'利润表'!C23,"") | D23: =IF(AND(AND('控制台'!B4<>"",'控制台'!B5<>"",'控制台'!B4='刷新信息'!B6,'控制台'!B5='刷新信息'!B8),COUNTIFS('预算输入'!A5:A204,'控制台'!B4,'预算输入'!B5:B204,'控制台'!B5,'预算输入'!C5:C204,A23)>0),SUMIFS('预算输入'!E5:E204,'预算输入'!A5:A204,'控制台'!B4,'预算输入'!B5:B204,'控制台'!B5,'预算输入'!C5:C204,A23),"") | E23: =IF(OR(D23="",C23=""),"",C23-D23) | F23: =IF(OR(D23="",D23=0),"",E23/ABS(D23))
A24: =IF('利润表'!A24="","",'利润表'!A24) | B24: =IF('利润表'!B24="","",'利润表'!B24) | C24: =IF(AND(AND('控制台'!B4<>"",'控制台'!B5<>"",'控制台'!B4='刷新信息'!B6,'控制台'!B5='刷新信息'!B8),ISNUMBER('利润表'!C24)),'利润表'!C24,"") | D24: =IF(AND(AND('控制台'!B4<>"",'控制台'!B5<>"",'控制台'!B4='刷新信息'!B6,'控制台'!B5='刷新信息'!B8),COUNTIFS('预算输入'!A5:A204,'控制台'!B4,'预算输入'!B5:B204,'控制台'!B5,'预算输入'!C5:C204,A24)>0),SUMIFS('预算输入'!E5:E204,'预算输入'!A5:A204,'控制台'!B4,'预算输入'!B5:B204,'控制台'!B5,'预算输入'!C5:C204,A24),"") | E24: =IF(OR(D24="",C24=""),"",C24-D24) | F24: =IF(OR(D24="",D24=0),"",E24/ABS(D24))
A25: =IF('利润表'!A25="","",'利润表'!A25) | B25: =IF('利润表'!B25="","",'利润表'!B25) | C25: =IF(AND(AND('控制台'!B4<>"",'控制台'!B5<>"",'控制台'!B4='刷新信息'!B6,'控制台'!B5='刷新信息'!B8),ISNUMBER('利润表'!C25)),'利润表'!C25,"") | D25: =IF(AND(AND('控制台'!B4<>"",'控制台'!B5<>"",'控制台'!B4='刷新信息'!B6,'控制台'!B5='刷新信息'!B8),COUNTIFS('预算输入'!A5:A204,'控制台'!B4,'预算输入'!B5:B204,'控制台'!B5,'预算输入'!C5:C204,A25)>0),SUMIFS('预算输入'!E5:E204,'预算输入'!A5:A204,'控制台'!B4,'预算输入'!B5:B204,'控制台'!B5,'预算输入'!C5:C204,A25),"") | E25: =IF(OR(D25="",C25=""),"",C25-D25) | F25: =IF(OR(D25="",D25=0),"",E25/ABS(D25))
A26: =IF('利润表'!A26="","",'利润表'!A26) | B26: =IF('利润表'!B26="","",'利润表'!B26) | C26: =IF(AND(AND('控制台'!B4<>"",'控制台'!B5<>"",'控制台'!B4='刷新信息'!B6,'控制台'!B5='刷新信息'!B8),ISNUMBER('利润表'!C26)),'利润表'!C26,"") | D26: =IF(AND(AND('控制台'!B4<>"",'控制台'!B5<>"",'控制台'!B4='刷新信息'!B6,'控制台'!B5='刷新信息'!B8),COUNTIFS('预算输入'!A5:A204,'控制台'!B4,'预算输入'!B5:B204,'控制台'!B5,'预算输入'!C5:C204,A26)>0),SUMIFS('预算输入'!E5:E204,'预算输入'!A5:A204,'控制台'!B4,'预算输入'!B5:B204,'控制台'!B5,'预算输入'!C5:C204,A26),"") | E26: =IF(OR(D26="",C26=""),"",C26-D26) | F26: =IF(OR(D26="",D26=0),"",E26/ABS(D26))
A27: =IF('利润表'!A27="","",'利润表'!A27) | B27: =IF('利润表'!B27="","",'利润表'!B27) | C27: =IF(AND(AND('控制台'!B4<>"",'控制台'!B5<>"",'控制台'!B4='刷新信息'!B6,'控制台'!B5='刷新信息'!B8),ISNUMBER('利润表'!C27)),'利润表'!C27,"") | D27: =IF(AND(AND('控制台'!B4<>"",'控制台'!B5<>"",'控制台'!B4='刷新信息'!B6,'控制台'!B5='刷新信息'!B8),COUNTIFS('预算输入'!A5:A204,'控制台'!B4,'预算输入'!B5:B204,'控制台'!B5,'预算输入'!C5:C204,A27)>0),SUMIFS('预算输入'!E5:E204,'预算输入'!A5:A204,'控制台'!B4,'预算输入'!B5:B204,'控制台'!B5,'预算输入'!C5:C204,A27),"") | E27: =IF(OR(D27="",C27=""),"",C27-D27) | F27: =IF(OR(D27="",D27=0),"",E27/ABS(D27))
A28: =IF('利润表'!A28="","",'利润表'!A28) | B28: =IF('利润表'!B28="","",'利润表'!B28) | C28: =IF(AND(AND('控制台'!B4<>"",'控制台'!B5<>"",'控制台'!B4='刷新信息'!B6,'控制台'!B5='刷新信息'!B8),ISNUMBER('利润表'!C28)),'利润表'!C28,"") | D28: =IF(AND(AND('控制台'!B4<>"",'控制台'!B5<>"",'控制台'!B4='刷新信息'!B6,'控制台'!B5='刷新信息'!B8),COUNTIFS('预算输入'!A5:A204,'控制台'!B4,'预算输入'!B5:B204,'控制台'!B5,'预算输入'!C5:C204,A28)>0),SUMIFS('预算输入'!E5:E204,'预算输入'!A5:A204,'控制台'!B4,'预算输入'!B5:B204,'控制台'!B5,'预算输入'!C5:C204,A28),"") | E28: =IF(OR(D28="",C28=""),"",C28-D28) | F28: =IF(OR(D28="",D28=0),"",E28/ABS(D28))
A29: =IF('利润表'!A29="","",'利润表'!A29) | B29: =IF('利润表'!B29="","",'利润表'!B29) | C29: =IF(AND(AND('控制台'!B4<>"",'控制台'!B5<>"",'控制台'!B4='刷新信息'!B6,'控制台'!B5='刷新信息'!B8),ISNUMBER('利润表'!C29)),'利润表'!C29,"") | D29: =IF(AND(AND('控制台'!B4<>"",'控制台'!B5<>"",'控制台'!B4='刷新信息'!B6,'控制台'!B5='刷新信息'!B8),COUNTIFS('预算输入'!A5:A204,'控制台'!B4,'预算输入'!B5:B204,'控制台'!B5,'预算输入'!C5:C204,A29)>0),SUMIFS('预算输入'!E5:E204,'预算输入'!A5:A204,'控制台'!B4,'预算输入'!B5:B204,'控制台'!B5,'预算输入'!C5:C204,A29),"") | E29: =IF(OR(D29="",C29=""),"",C29-D29) | F29: =IF(OR(D29="",D29=0),"",E29/ABS(D29))
A30: =IF('利润表'!A30="","",'利润表'!A30) | B30: =IF('利润表'!B30="","",'利润表'!B30) | C30: =IF(AND(AND('控制台'!B4<>"",'控制台'!B5<>"",'控制台'!B4='刷新信息'!B6,'控制台'!B5='刷新信息'!B8),ISNUMBER('利润表'!C30)),'利润表'!C30,"") | D30: =IF(AND(AND('控制台'!B4<>"",'控制台'!B5<>"",'控制台'!B4='刷新信息'!B6,'控制台'!B5='刷新信息'!B8),COUNTIFS('预算输入'!A5:A204,'控制台'!B4,'预算输入'!B5:B204,'控制台'!B5,'预算输入'!C5:C204,A30)>0),SUMIFS('预算输入'!E5:E204,'预算输入'!A5:A204,'控制台'!B4,'预算输入'!B5:B204,'控制台'!B5,'预算输入'!C5:C204,A30),"") | E30: =IF(OR(D30="",C30=""),"",C30-D30) | F30: =IF(OR(D30="",D30=0),"",E30/ABS(D30))
A31: =IF('利润表'!A31="","",'利润表'!A31) | B31: =IF('利润表'!B31="","",'利润表'!B31) | C31: =IF(AND(AND('控制台'!B4<>"",'控制台'!B5<>"",'控制台'!B4='刷新信息'!B6,'控制台'!B5='刷新信息'!B8),ISNUMBER('利润表'!C31)),'利润表'!C31,"") | D31: =IF(AND(AND('控制台'!B4<>"",'控制台'!B5<>"",'控制台'!B4='刷新信息'!B6,'控制台'!B5='刷新信息'!B8),COUNTIFS('预算输入'!A5:A204,'控制台'!B4,'预算输入'!B5:B204,'控制台'!B5,'预算输入'!C5:C204,A31)>0),SUMIFS('预算输入'!E5:E204,'预算输入'!A5:A204,'控制台'!B4,'预算输入'!B5:B204,'控制台'!B5,'预算输入'!C5:C204,A31),"") | E31: =IF(OR(D31="",C31=""),"",C31-D31) | F31: =IF(OR(D31="",D31=0),"",E31/ABS(D31))
A32: =IF('利润表'!A32="","",'利润表'!A32) | B32: =IF('利润表'!B32="","",'利润表'!B32) | C32: =IF(AND(AND('控制台'!B4<>"",'控制台'!B5<>"",'控制台'!B4='刷新信息'!B6,'控制台'!B5='刷新信息'!B8),ISNUMBER('利润表'!C32)),'利润表'!C32,"") | D32: =IF(AND(AND('控制台'!B4<>"",'控制台'!B5<>"",'控制台'!B4='刷新信息'!B6,'控制台'!B5='刷新信息'!B8),COUNTIFS('预算输入'!A5:A204,'控制台'!B4,'预算输入'!B5:B204,'控制台'!B5,'预算输入'!C5:C204,A32)>0),SUMIFS('预算输入'!E5:E204,'预算输入'!A5:A204,'控制台'!B4,'预算输入'!B5:B204,'控制台'!B5,'预算输入'!C5:C204,A32),"") | E32: =IF(OR(D32="",C32=""),"",C32-D32) | F32: =IF(OR(D32="",D32=0),"",E32/ABS(D32))
A33: =IF('利润表'!A33="","",'利润表'!A33) | B33: =IF('利润表'!B33="","",'利润表'!B33) | C33: =IF(AND(AND('控制台'!B4<>"",'控制台'!B5<>"",'控制台'!B4='刷新信息'!B6,'控制台'!B5='刷新信息'!B8),ISNUMBER('利润表'!C33)),'利润表'!C33,"") | D33: =IF(AND(AND('控制台'!B4<>"",'控制台'!B5<>"",'控制台'!B4='刷新信息'!B6,'控制台'!B5='刷新信息'!B8),COUNTIFS('预算输入'!A5:A204,'控制台'!B4,'预算输入'!B5:B204,'控制台'!B5,'预算输入'!C5:C204,A33)>0),SUMIFS('预算输入'!E5:E204,'预算输入'!A5:A204,'控制台'!B4,'预算输入'!B5:B204,'控制台'!B5,'预算输入'!C5:C204,A33),"") | E33: =IF(OR(D33="",C33=""),"",C33-D33) | F33: =IF(OR(D33="",D33=0),"",E33/ABS(D33))
A34: =IF('利润表'!A34="","",'利润表'!A34) | B34: =IF('利润表'!B34="","",'利润表'!B34) | C34: =IF(AND(AND('控制台'!B4<>"",'控制台'!B5<>"",'控制台'!B4='刷新信息'!B6,'控制台'!B5='刷新信息'!B8),ISNUMBER('利润表'!C34)),'利润表'!C34,"") | D34: =IF(AND(AND('控制台'!B4<>"",'控制台'!B5<>"",'控制台'!B4='刷新信息'!B6,'控制台'!B5='刷新信息'!B8),COUNTIFS('预算输入'!A5:A204,'控制台'!B4,'预算输入'!B5:B204,'控制台'!B5,'预算输入'!C5:C204,A34)>0),SUMIFS('预算输入'!E5:E204,'预算输入'!A5:A204,'控制台'!B4,'预算输入'!B5:B204,'控制台'!B5,'预算输入'!C5:C204,A34),"") | E34: =IF(OR(D34="",C34=""),"",C34-D34) | F34: =IF(OR(D34="",D34=0),"",E34/ABS(D34))
A35: =IF('利润表'!A35="","",'利润表'!A35) | B35: =IF('利润表'!B35="","",'利润表'!B35) | C35: =IF(AND(AND('控制台'!B4<>"",'控制台'!B5<>"",'控制台'!B4='刷新信息'!B6,'控制台'!B5='刷新信息'!B8),ISNUMBER('利润表'!C35)),'利润表'!C35,"") | D35: =IF(AND(AND('控制台'!B4<>"",'控制台'!B5<>"",'控制台'!B4='刷新信息'!B6,'控制台'!B5='刷新信息'!B8),COUNTIFS('预算输入'!A5:A204,'控制台'!B4,'预算输入'!B5:B204,'控制台'!B5,'预算输入'!C5:C204,A35)>0),SUMIFS('预算输入'!E5:E204,'预算输入'!A5:A204,'控制台'!B4,'预算输入'!B5:B204,'控制台'!B5,'预算输入'!C5:C204,A35),"") | E35: =IF(OR(D35="",C35=""),"",C35-D35) | F35: =IF(OR(D35="",D35=0),"",E35/ABS(D35))
A36: =IF('利润表'!A36="","",'利润表'!A36) | B36: =IF('利润表'!B36="","",'利润表'!B36) | C36: =IF(AND(AND('控制台'!B4<>"",'控制台'!B5<>"",'控制台'!B4='刷新信息'!B6,'控制台'!B5='刷新信息'!B8),ISNUMBER('利润表'!C36)),'利润表'!C36,"") | D36: =IF(AND(AND('控制台'!B4<>"",'控制台'!B5<>"",'控制台'!B4='刷新信息'!B6,'控制台'!B5='刷新信息'!B8),COUNTIFS('预算输入'!A5:A204,'控制台'!B4,'预算输入'!B5:B204,'控制台'!B5,'预算输入'!C5:C204,A36)>0),SUMIFS('预算输入'!E5:E204,'预算输入'!A5:A204,'控制台'!B4,'预算输入'!B5:B204,'控制台'!B5,'预算输入'!C5:C204,A36),"") | E36: =IF(OR(D36="",C36=""),"",C36-D36) | F36: =IF(OR(D36="",D36=0),"",E36/ABS(D36))

Sheet 账龄输入
A1: 未核销单据输入
A2: 金额为截至所选月末仍未核销的人民币余额；不是发票原始总额。项目ID从往来余额复制。
A4: 公司编号 | B4: 月份 | C4: 应收/应付 | D4: 核算项目ID组合 | E4: 单据编号 | F4: 发生日期 | G4: 到期日期 | H4: 未核销金额 | I4: 账龄天数 | J4: 逾期天数 | K4: 核验
I5: =IF(OR(A5<> '控制台'!B4,B5<> '控制台'!B5,F5=""),"",DATE(VALUE(LEFT('控制台'!B5,4)),VALUE(RIGHT('控制台'!B5,2))+1,1)-1-F5) | J5: =IF(OR(A5<> '控制台'!B4,B5<> '控制台'!B5,G5=""),"",MAX(0,DATE(VALUE(LEFT('控制台'!B5,4)),VALUE(RIGHT('控制台'!B5,2))+1,1)-1-G5)) | K5: =IF(A5="","",IF(AND(AND('控制台'!B4<>"",'控制台'!B5<>"",'控制台'!B4='刷新信息'!B6,'控制台'!B5='刷新信息'!B8),A5='控制台'!B4,B5='控制台'!B5,OR(C5="应收",C5="应付"),COUNTIFS('往来余额'!A5:A6000,C5,'往来余额'!B5:B6000,D5)=1,E5<>"",COUNTIFS(A$5:A$504,A5,B$5:B$504,B5,C$5:C$504,C5,D$5:D$504,D5,E$5:E$504,E5)=1,ISNUMBER(F5),I5>=0,ISNUMBER(H5),H5>=0),"纳入","待核实"))
I6: =IF(OR(A6<> '控制台'!B4,B6<> '控制台'!B5,F6=""),"",DATE(VALUE(LEFT('控制台'!B5,4)),VALUE(RIGHT('控制台'!B5,2))+1,1)-1-F6) | J6: =IF(OR(A6<> '控制台'!B4,B6<> '控制台'!B5,G6=""),"",MAX(0,DATE(VALUE(LEFT('控制台'!B5,4)),VALUE(RIGHT('控制台'!B5,2))+1,1)-1-G6)) | K6: =IF(A6="","",IF(AND(AND('控制台'!B4<>"",'控制台'!B5<>"",'控制台'!B4='刷新信息'!B6,'控制台'!B5='刷新信息'!B8),A6='控制台'!B4,B6='控制台'!B5,OR(C6="应收",C6="应付"),COUNTIFS('往来余额'!A5:A6000,C6,'往来余额'!B5:B6000,D6)=1,E6<>"",COUNTIFS(A$5:A$504,A6,B$5:B$504,B6,C$5:C$504,C6,D$5:D$504,D6,E$5:E$504,E6)=1,ISNUMBER(F6),I6>=0,ISNUMBER(H6),H6>=0),"纳入","待核实"))
I7: =IF(OR(A7<> '控制台'!B4,B7<> '控制台'!B5,F7=""),"",DATE(VALUE(LEFT('控制台'!B5,4)),VALUE(RIGHT('控制台'!B5,2))+1,1)-1-F7) | J7: =IF(OR(A7<> '控制台'!B4,B7<> '控制台'!B5,G7=""),"",MAX(0,DATE(VALUE(LEFT('控制台'!B5,4)),VALUE(RIGHT('控制台'!B5,2))+1,1)-1-G7)) | K7: =IF(A7="","",IF(AND(AND('控制台'!B4<>"",'控制台'!B5<>"",'控制台'!B4='刷新信息'!B6,'控制台'!B5='刷新信息'!B8),A7='控制台'!B4,B7='控制台'!B5,OR(C7="应收",C7="应付"),COUNTIFS('往来余额'!A5:A6000,C7,'往来余额'!B5:B6000,D7)=1,E7<>"",COUNTIFS(A$5:A$504,A7,B$5:B$504,B7,C$5:C$504,C7,D$5:D$504,D7,E$5:E$504,E7)=1,ISNUMBER(F7),I7>=0,ISNUMBER(H7),H7>=0),"纳入","待核实"))
I8: =IF(OR(A8<> '控制台'!B4,B8<> '控制台'!B5,F8=""),"",DATE(VALUE(LEFT('控制台'!B5,4)),VALUE(RIGHT('控制台'!B5,2))+1,1)-1-F8) | J8: =IF(OR(A8<> '控制台'!B4,B8<> '控制台'!B5,G8=""),"",MAX(0,DATE(VALUE(LEFT('控制台'!B5,4)),VALUE(RIGHT('控制台'!B5,2))+1,1)-1-G8)) | K8: =IF(A8="","",IF(AND(AND('控制台'!B4<>"",'控制台'!B5<>"",'控制台'!B4='刷新信息'!B6,'控制台'!B5='刷新信息'!B8),A8='控制台'!B4,B8='控制台'!B5,OR(C8="应收",C8="应付"),COUNTIFS('往来余额'!A5:A6000,C8,'往来余额'!B5:B6000,D8)=1,E8<>"",COUNTIFS(A$5:A$504,A8,B$5:B$504,B8,C$5:C$504,C8,D$5:D$504,D8,E$5:E$504,E8)=1,ISNUMBER(F8),I8>=0,ISNUMBER(H8),H8>=0),"纳入","待核实"))
I9: =IF(OR(A9<> '控制台'!B4,B9<> '控制台'!B5,F9=""),"",DATE(VALUE(LEFT('控制台'!B5,4)),VALUE(RIGHT('控制台'!B5,2))+1,1)-1-F9) | J9: =IF(OR(A9<> '控制台'!B4,B9<> '控制台'!B5,G9=""),"",MAX(0,DATE(VALUE(LEFT('控制台'!B5,4)),VALUE(RIGHT('控制台'!B5,2))+1,1)-1-G9)) | K9: =IF(A9="","",IF(AND(AND('控制台'!B4<>"",'控制台'!B5<>"",'控制台'!B4='刷新信息'!B6,'控制台'!B5='刷新信息'!B8),A9='控制台'!B4,B9='控制台'!B5,OR(C9="应收",C9="应付"),COUNTIFS('往来余额'!A5:A6000,C9,'往来余额'!B5:B6000,D9)=1,E9<>"",COUNTIFS(A$5:A$504,A9,B$5:B$504,B9,C$5:C$504,C9,D$5:D$504,D9,E$5:E$504,E9)=1,ISNUMBER(F9),I9>=0,ISNUMBER(H9),H9>=0),"纳入","待核实"))
I10: =IF(OR(A10<> '控制台'!B4,B10<> '控制台'!B5,F10=""),"",DATE(VALUE(LEFT('控制台'!B5,4)),VALUE(RIGHT('控制台'!B5,2))+1,1)-1-F10) | J10: =IF(OR(A10<> '控制台'!B4,B10<> '控制台'!B5,G10=""),"",MAX(0,DATE(VALUE(LEFT('控制台'!B5,4)),VALUE(RIGHT('控制台'!B5,2))+1,1)-1-G10)) | K10: =IF(A10="","",IF(AND(AND('控制台'!B4<>"",'控制台'!B5<>"",'控制台'!B4='刷新信息'!B6,'控制台'!B5='刷新信息'!B8),A10='控制台'!B4,B10='控制台'!B5,OR(C10="应收",C10="应付"),COUNTIFS('往来余额'!A5:A6000,C10,'往来余额'!B5:B6000,D10)=1,E10<>"",COUNTIFS(A$5:A$504,A10,B$5:B$504,B10,C$5:C$504,C10,D$5:D$504,D10,E$5:E$504,E10)=1,ISNUMBER(F10),I10>=0,ISNUMBER(H10),H10>=0),"纳入","待核实"))
I11: =IF(OR(A11<> '控制台'!B4,B11<> '控制台'!B5,F11=""),"",DATE(VALUE(LEFT('控制台'!B5,4)),VALUE(RIGHT('控制台'!B5,2))+1,1)-1-F11) | J11: =IF(OR(A11<> '控制台'!B4,B11<> '控制台'!B5,G11=""),"",MAX(0,DATE(VALUE(LEFT('控制台'!B5,4)),VALUE(RIGHT('控制台'!B5,2))+1,1)-1-G11)) | K11: =IF(A11="","",IF(AND(AND('控制台'!B4<>"",'控制台'!B5<>"",'控制台'!B4='刷新信息'!B6,'控制台'!B5='刷新信息'!B8),A11='控制台'!B4,B11='控制台'!B5,OR(C11="应收",C11="应付"),COUNTIFS('往来余额'!A5:A6000,C11,'往来余额'!B5:B6000,D11)=1,E11<>"",COUNTIFS(A$5:A$504,A11,B$5:B$504,B11,C$5:C$504,C11,D$5:D$504,D11,E$5:E$504,E11)=1,ISNUMBER(F11),I11>=0,ISNUMBER(H11),H11>=0),"纳入","待核实"))
I12: =IF(OR(A12<> '控制台'!B4,B12<> '控制台'!B5,F12=""),"",DATE(VALUE(LEFT('控制台'!B5,4)),VALUE(RIGHT('控制台'!B5,2))+1,1)-1-F12) | J12: =IF(OR(A12<> '控制台'!B4,B12<> '控制台'!B5,G12=""),"",MAX(0,DATE(VALUE(LEFT('控制台'!B5,4)),VALUE(RIGHT('控制台'!B5,2))+1,1)-1-G12)) | K12: =IF(A12="","",IF(AND(AND('控制台'!B4<>"",'控制台'!B5<>"",'控制台'!B4='刷新信息'!B6,'控制台'!B5='刷新信息'!B8),A12='控制台'!B4,B12='控制台'!B5,OR(C12="应收",C12="应付"),COUNTIFS('往来余额'!A5:A6000,C12,'往来余额'!B5:B6000,D12)=1,E12<>"",COUNTIFS(A$5:A$504,A12,B$5:B$504,B12,C$5:C$504,C12,D$5:D$504,D12,E$5:E$504,E12)=1,ISNUMBER(F12),I12>=0,ISNUMBER(H12),H12>=0),"纳入","待核实"))
I13: =IF(OR(A13<> '控制台'!B4,B13<> '控制台'!B5,F13=""),"",DATE(VALUE(LEFT('控制台'!B5,4)),VALUE(RIGHT('控制台'!B5,2))+1,1)-1-F13) | J13: =IF(OR(A13<> '控制台'!B4,B13<> '控制台'!B5,G13=""),"",MAX(0,DATE(VALUE(LEFT('控制台'!B5,4)),VALUE(RIGHT('控制台'!B5,2))+1,1)-1-G13)) | K13: =IF(A13="","",IF(AND(AND('控制台'!B4<>"",'控制台'!B5<>"",'控制台'!B4='刷新信息'!B6,'控制台'!B5='刷新信息'!B8),A13='控制台'!B4,B13='控制台'!B5,OR(C13="应收",C13="应付"),COUNTIFS('往来余额'!A5:A6000,C13,'往来余额'!B5:B6000,D13)=1,E13<>"",COUNTIFS(A$5:A$504,A13,B$5:B$504,B13,C$5:C$504,C13,D$5:D$504,D13,E$5:E$504,E13)=1,ISNUMBER(F13),I13>=0,ISNUMBER(H13),H13>=0),"纳入","待核实"))
I14: =IF(OR(A14<> '控制台'!B4,B14<> '控制台'!B5,F14=""),"",DATE(VALUE(LEFT('控制台'!B5,4)),VALUE(RIGHT('控制台'!B5,2))+1,1)-1-F14) | J14: =IF(OR(A14<> '控制台'!B4,B14<> '控制台'!B5,G14=""),"",MAX(0,DATE(VALUE(LEFT('控制台'!B5,4)),VALUE(RIGHT('控制台'!B5,2))+1,1)-1-G14)) | K14: =IF(A14="","",IF(AND(AND('控制台'!B4<>"",'控制台'!B5<>"",'控制台'!B4='刷新信息'!B6,'控制台'!B5='刷新信息'!B8),A14='控制台'!B4,B14='控制台'!B5,OR(C14="应收",C14="应付"),COUNTIFS('往来余额'!A5:A6000,C14,'往来余额'!B5:B6000,D14)=1,E14<>"",COUNTIFS(A$5:A$504,A14,B$5:B$504,B14,C$5:C$504,C14,D$5:D$504,D14,E$5:E$504,E14)=1,ISNUMBER(F14),I14>=0,ISNUMBER(H14),H14>=0),"纳入","待核实"))
I15: =IF(OR(A15<> '控制台'!B4,B15<> '控制台'!B5,F15=""),"",DATE(VALUE(LEFT('控制台'!B5,4)),VALUE(RIGHT('控制台'!B5,2))+1,1)-1-F15) | J15: =IF(OR(A15<> '控制台'!B4,B15<> '控制台'!B5,G15=""),"",MAX(0,DATE(VALUE(LEFT('控制台'!B5,4)),VALUE(RIGHT('控制台'!B5,2))+1,1)-1-G15)) | K15: =IF(A15="","",IF(AND(AND('控制台'!B4<>"",'控制台'!B5<>"",'控制台'!B4='刷新信息'!B6,'控制台'!B5='刷新信息'!B8),A15='控制台'!B4,B15='控制台'!B5,OR(C15="应收",C15="应付"),COUNTIFS('往来余额'!A5:A6000,C15,'往来余额'!B5:B6000,D15)=1,E15<>"",COUNTIFS(A$5:A$504,A15,B$5:B$504,B15,C$5:C$504,C15,D$5:D$504,D15,E$5:E$504,E15)=1,ISNUMBER(F15),I15>=0,ISNUMBER(H15),H15>=0),"纳入","待核实"))
I16: =IF(OR(A16<> '控制台'!B4,B16<> '控制台'!B5,F16=""),"",DATE(VALUE(LEFT('控制台'!B5,4)),VALUE(RIGHT('控制台'!B5,2))+1,1)-1-F16) | J16: =IF(OR(A16<> '控制台'!B4,B16<> '控制台'!B5,G16=""),"",MAX(0,DATE(VALUE(LEFT('控制台'!B5,4)),VALUE(RIGHT('控制台'!B5,2))+1,1)-1-G16)) | K16: =IF(A16="","",IF(AND(AND('控制台'!B4<>"",'控制台'!B5<>"",'控制台'!B4='刷新信息'!B6,'控制台'!B5='刷新信息'!B8),A16='控制台'!B4,B16='控制台'!B5,OR(C16="应收",C16="应付"),COUNTIFS('往来余额'!A5:A6000,C16,'往来余额'!B5:B6000,D16)=1,E16<>"",COUNTIFS(A$5:A$504,A16,B$5:B$504,B16,C$5:C$504,C16,D$5:D$504,D16,E$5:E$504,E16)=1,ISNUMBER(F16),I16>=0,ISNUMBER(H16),H16>=0),"纳入","待核实"))
I17: =IF(OR(A17<> '控制台'!B4,B17<> '控制台'!B5,F17=""),"",DATE(VALUE(LEFT('控制台'!B5,4)),VALUE(RIGHT('控制台'!B5,2))+1,1)-1-F17) | J17: =IF(OR(A17<> '控制台'!B4,B17<> '控制台'!B5,G17=""),"",MAX(0,DATE(VALUE(LEFT('控制台'!B5,4)),VALUE(RIGHT('控制台'!B5,2))+1,1)-1-G17)) | K17: =IF(A17="","",IF(AND(AND('控制台'!B4<>"",'控制台'!B5<>"",'控制台'!B4='刷新信息'!B6,'控制台'!B5='刷新信息'!B8),A17='控制台'!B4,B17='控制台'!B5,OR(C17="应收",C17="应付"),COUNTIFS('往来余额'!A5:A6000,C17,'往来余额'!B5:B6000,D17)=1,E17<>"",COUNTIFS(A$5:A$504,A17,B$5:B$504,B17,C$5:C$504,C17,D$5:D$504,D17,E$5:E$504,E17)=1,ISNUMBER(F17),I17>=0,ISNUMBER(H17),H17>=0),"纳入","待核实"))
I18: =IF(OR(A18<> '控制台'!B4,B18<> '控制台'!B5,F18=""),"",DATE(VALUE(LEFT('控制台'!B5,4)),VALUE(RIGHT('控制台'!B5,2))+1,1)-1-F18) | J18: =IF(OR(A18<> '控制台'!B4,B18<> '控制台'!B5,G18=""),"",MAX(0,DATE(VALUE(LEFT('控制台'!B5,4)),VALUE(RIGHT('控制台'!B5,2))+1,1)-1-G18)) | K18: =IF(A18="","",IF(AND(AND('控制台'!B4<>"",'控制台'!B5<>"",'控制台'!B4='刷新信息'!B6,'控制台'!B5='刷新信息'!B8),A18='控制台'!B4,B18='控制台'!B5,OR(C18="应收",C18="应付"),COUNTIFS('往来余额'!A5:A6000,C18,'往来余额'!B5:B6000,D18)=1,E18<>"",COUNTIFS(A$5:A$504,A18,B$5:B$504,B18,C$5:C$504,C18,D$5:D$504,D18,E$5:E$504,E18)=1,ISNUMBER(F18),I18>=0,ISNUMBER(H18),H18>=0),"纳入","待核实"))
I19: =IF(OR(A19<> '控制台'!B4,B19<> '控制台'!B5,F19=""),"",DATE(VALUE(LEFT('控制台'!B5,4)),VALUE(RIGHT('控制台'!B5,2))+1,1)-1-F19) | J19: =IF(OR(A19<> '控制台'!B4,B19<> '控制台'!B5,G19=""),"",MAX(0,DATE(VALUE(LEFT('控制台'!B5,4)),VALUE(RIGHT('控制台'!B5,2))+1,1)-1-G19)) | K19: =IF(A19="","",IF(AND(AND('控制台'!B4<>"",'控制台'!B5<>"",'控制台'!B4='刷新信息'!B6,'控制台'!B5='刷新信息'!B8),A19='控制台'!B4,B19='控制台'!B5,OR(C19="应收",C19="应付"),COUNTIFS('往来余额'!A5:A6000,C19,'往来余额'!B5:B6000,D19)=1,E19<>"",COUNTIFS(A$5:A$504,A19,B$5:B$504,B19,C$5:C$504,C19,D$5:D$504,D19,E$5:E$504,E19)=1,ISNUMBER(F19),I19>=0,ISNUMBER(H19),H19>=0),"纳入","待核实"))
I20: =IF(OR(A20<> '控制台'!B4,B20<> '控制台'!B5,F20=""),"",DATE(VALUE(LEFT('控制台'!B5,4)),VALUE(RIGHT('控制台'!B5,2))+1,1)-1-F20) | J20: =IF(OR(A20<> '控制台'!B4,B20<> '控制台'!B5,G20=""),"",MAX(0,DATE(VALUE(LEFT('控制台'!B5,4)),VALUE(RIGHT('控制台'!B5,2))+1,1)-1-G20)) | K20: =IF(A20="","",IF(AND(AND('控制台'!B4<>"",'控制台'!B5<>"",'控制台'!B4='刷新信息'!B6,'控制台'!B5='刷新信息'!B8),A20='控制台'!B4,B20='控制台'!B5,OR(C20="应收",C20="应付"),COUNTIFS('往来余额'!A5:A6000,C20,'往来余额'!B5:B6000,D20)=1,E20<>"",COUNTIFS(A$5:A$504,A20,B$5:B$504,B20,C$5:C$504,C20,D$5:D$504,D20,E$5:E$504,E20)=1,ISNUMBER(F20),I20>=0,ISNUMBER(H20),H20>=0),"纳入","待核实"))
I21: =IF(OR(A21<> '控制台'!B4,B21<> '控制台'!B5,F21=""),"",DATE(VALUE(LEFT('控制台'!B5,4)),VALUE(RIGHT('控制台'!B5,2))+1,1)-1-F21) | J21: =IF(OR(A21<> '控制台'!B4,B21<> '控制台'!B5,G21=""),"",MAX(0,DATE(VALUE(LEFT('控制台'!B5,4)),VALUE(RIGHT('控制台'!B5,2))+1,1)-1-G21)) | K21: =IF(A21="","",IF(AND(AND('控制台'!B4<>"",'控制台'!B5<>"",'控制台'!B4='刷新信息'!B6,'控制台'!B5='刷新信息'!B8),A21='控制台'!B4,B21='控制台'!B5,OR(C21="应收",C21="应付"),COUNTIFS('往来余额'!A5:A6000,C21,'往来余额'!B5:B6000,D21)=1,E21<>"",COUNTIFS(A$5:A$504,A21,B$5:B$504,B21,C$5:C$504,C21,D$5:D$504,D21,E$5:E$504,E21)=1,ISNUMBER(F21),I21>=0,ISNUMBER(H21),H21>=0),"纳入","待核实"))
I22: =IF(OR(A22<> '控制台'!B4,B22<> '控制台'!B5,F22=""),"",DATE(VALUE(LEFT('控制台'!B5,4)),VALUE(RIGHT('控制台'!B5,2))+1,1)-1-F22) | J22: =IF(OR(A22<> '控制台'!B4,B22<> '控制台'!B5,G22=""),"",MAX(0,DATE(VALUE(LEFT('控制台'!B5,4)),VALUE(RIGHT('控制台'!B5,2))+1,1)-1-G22)) | K22: =IF(A22="","",IF(AND(AND('控制台'!B4<>"",'控制台'!B5<>"",'控制台'!B4='刷新信息'!B6,'控制台'!B5='刷新信息'!B8),A22='控制台'!B4,B22='控制台'!B5,OR(C22="应收",C22="应付"),COUNTIFS('往来余额'!A5:A6000,C22,'往来余额'!B5:B6000,D22)=1,E22<>"",COUNTIFS(A$5:A$504,A22,B$5:B$504,B22,C$5:C$504,C22,D$5:D$504,D22,E$5:E$504,E22)=1,ISNUMBER(F22),I22>=0,ISNUMBER(H22),H22>=0),"纳入","待核实"))
I23: =IF(OR(A23<> '控制台'!B4,B23<> '控制台'!B5,F23=""),"",DATE(VALUE(LEFT('控制台'!B5,4)),VALUE(RIGHT('控制台'!B5,2))+1,1)-1-F23) | J23: =IF(OR(A23<> '控制台'!B4,B23<> '控制台'!B5,G23=""),"",MAX(0,DATE(VALUE(LEFT('控制台'!B5,4)),VALUE(RIGHT('控制台'!B5,2))+1,1)-1-G23)) | K23: =IF(A23="","",IF(AND(AND('控制台'!B4<>"",'控制台'!B5<>"",'控制台'!B4='刷新信息'!B6,'控制台'!B5='刷新信息'!B8),A23='控制台'!B4,B23='控制台'!B5,OR(C23="应收",C23="应付"),COUNTIFS('往来余额'!A5:A6000,C23,'往来余额'!B5:B6000,D23)=1,E23<>"",COUNTIFS(A$5:A$504,A23,B$5:B$504,B23,C$5:C$504,C23,D$5:D$504,D23,E$5:E$504,E23)=1,ISNUMBER(F23),I23>=0,ISNUMBER(H23),H23>=0),"纳入","待核实"))
I24: =IF(OR(A24<> '控制台'!B4,B24<> '控制台'!B5,F24=""),"",DATE(VALUE(LEFT('控制台'!B5,4)),VALUE(RIGHT('控制台'!B5,2))+1,1)-1-F24) | J24: =IF(OR(A24<> '控制台'!B4,B24<> '控制台'!B5,G24=""),"",MAX(0,DATE(VALUE(LEFT('控制台'!B5,4)),VALUE(RIGHT('控制台'!B5,2))+1,1)-1-G24)) | K24: =IF(A24="","",IF(AND(AND('控制台'!B4<>"",'控制台'!B5<>"",'控制台'!B4='刷新信息'!B6,'控制台'!B5='刷新信息'!B8),A24='控制台'!B4,B24='控制台'!B5,OR(C24="应收",C24="应付"),COUNTIFS('往来余额'!A5:A6000,C24,'往来余额'!B5:B6000,D24)=1,E24<>"",COUNTIFS(A$5:A$504,A24,B$5:B$504,B24,C$5:C$504,C24,D$5:D$504,D24,E$5:E$504,E24)=1,ISNUMBER(F24),I24>=0,ISNUMBER(H24),H24>=0),"纳入","待核实"))
I25: =IF(OR(A25<> '控制台'!B4,B25<> '控制台'!B5,F25=""),"",DATE(VALUE(LEFT('控制台'!B5,4)),VALUE(RIGHT('控制台'!B5,2))+1,1)-1-F25) | J25: =IF(OR(A25<> '控制台'!B4,B25<> '控制台'!B5,G25=""),"",MAX(0,DATE(VALUE(LEFT('控制台'!B5,4)),VALUE(RIGHT('控制台'!B5,2))+1,1)-1-G25)) | K25: =IF(A25="","",IF(AND(AND('控制台'!B4<>"",'控制台'!B5<>"",'控制台'!B4='刷新信息'!B6,'控制台'!B5='刷新信息'!B8),A25='控制台'!B4,B25='控制台'!B5,OR(C25="应收",C25="应付"),COUNTIFS('往来余额'!A5:A6000,C25,'往来余额'!B5:B6000,D25)=1,E25<>"",COUNTIFS(A$5:A$504,A25,B$5:B$504,B25,C$5:C$504,C25,D$5:D$504,D25,E$5:E$504,E25)=1,ISNUMBER(F25),I25>=0,ISNUMBER(H25),H25>=0),"纳入","待核实"))
I26: =IF(OR(A26<> '控制台'!B4,B26<> '控制台'!B5,F26=""),"",DATE(VALUE(LEFT('控制台'!B5,4)),VALUE(RIGHT('控制台'!B5,2))+1,1)-1-F26) | J26: =IF(OR(A26<> '控制台'!B4,B26<> '控制台'!B5,G26=""),"",MAX(0,DATE(VALUE(LEFT('控制台'!B5,4)),VALUE(RIGHT('控制台'!B5,2))+1,1)-1-G26)) | K26: =IF(A26="","",IF(AND(AND('控制台'!B4<>"",'控制台'!B5<>"",'控制台'!B4='刷新信息'!B6,'控制台'!B5='刷新信息'!B8),A26='控制台'!B4,B26='控制台'!B5,OR(C26="应收",C26="应付"),COUNTIFS('往来余额'!A5:A6000,C26,'往来余额'!B5:B6000,D26)=1,E26<>"",COUNTIFS(A$5:A$504,A26,B$5:B$504,B26,C$5:C$504,C26,D$5:D$504,D26,E$5:E$504,E26)=1,ISNUMBER(F26),I26>=0,ISNUMBER(H26),H26>=0),"纳入","待核实"))
I27: =IF(OR(A27<> '控制台'!B4,B27<> '控制台'!B5,F27=""),"",DATE(VALUE(LEFT('控制台'!B5,4)),VALUE(RIGHT('控制台'!B5,2))+1,1)-1-F27) | J27: =IF(OR(A27<> '控制台'!B4,B27<> '控制台'!B5,G27=""),"",MAX(0,DATE(VALUE(LEFT('控制台'!B5,4)),VALUE(RIGHT('控制台'!B5,2))+1,1)-1-G27)) | K27: =IF(A27="","",IF(AND(AND('控制台'!B4<>"",'控制台'!B5<>"",'控制台'!B4='刷新信息'!B6,'控制台'!B5='刷新信息'!B8),A27='控制台'!B4,B27='控制台'!B5,OR(C27="应收",C27="应付"),COUNTIFS('往来余额'!A5:A6000,C27,'往来余额'!B5:B6000,D27)=1,E27<>"",COUNTIFS(A$5:A$504,A27,B$5:B$504,B27,C$5:C$504,C27,D$5:D$504,D27,E$5:E$504,E27)=1,ISNUMBER(F27),I27>=0,ISNUMBER(H27),H27>=0),"纳入","待核实"))
I28: =IF(OR(A28<> '控制台'!B4,B28<> '控制台'!B5,F28=""),"",DATE(VALUE(LEFT('控制台'!B5,4)),VALUE(RIGHT('控制台'!B5,2))+1,1)-1-F28) | J28: =IF(OR(A28<> '控制台'!B4,B28<> '控制台'!B5,G28=""),"",MAX(0,DATE(VALUE(LEFT('控制台'!B5,4)),VALUE(RIGHT('控制台'!B5,2))+1,1)-1-G28)) | K28: =IF(A28="","",IF(AND(AND('控制台'!B4<>"",'控制台'!B5<>"",'控制台'!B4='刷新信息'!B6,'控制台'!B5='刷新信息'!B8),A28='控制台'!B4,B28='控制台'!B5,OR(C28="应收",C28="应付"),COUNTIFS('往来余额'!A5:A6000,C28,'往来余额'!B5:B6000,D28)=1,E28<>"",COUNTIFS(A$5:A$504,A28,B$5:B$504,B28,C$5:C$504,C28,D$5:D$504,D28,E$5:E$504,E28)=1,ISNUMBER(F28),I28>=0,ISNUMBER(H28),H28>=0),"纳入","待核实"))
I29: =IF(OR(A29<> '控制台'!B4,B29<> '控制台'!B5,F29=""),"",DATE(VALUE(LEFT('控制台'!B5,4)),VALUE(RIGHT('控制台'!B5,2))+1,1)-1-F29) | J29: =IF(OR(A29<> '控制台'!B4,B29<> '控制台'!B5,G29=""),"",MAX(0,DATE(VALUE(LEFT('控制台'!B5,4)),VALUE(RIGHT('控制台'!B5,2))+1,1)-1-G29)) | K29: =IF(A29="","",IF(AND(AND('控制台'!B4<>"",'控制台'!B5<>"",'控制台'!B4='刷新信息'!B6,'控制台'!B5='刷新信息'!B8),A29='控制台'!B4,B29='控制台'!B5,OR(C29="应收",C29="应付"),COUNTIFS('往来余额'!A5:A6000,C29,'往来余额'!B5:B6000,D29)=1,E29<>"",COUNTIFS(A$5:A$504,A29,B$5:B$504,B29,C$5:C$504,C29,D$5:D$504,D29,E$5:E$504,E29)=1,ISNUMBER(F29),I29>=0,ISNUMBER(H29),H29>=0),"纳入","待核实"))
I30: =IF(OR(A30<> '控制台'!B4,B30<> '控制台'!B5,F30=""),"",DATE(VALUE(LEFT('控制台'!B5,4)),VALUE(RIGHT('控制台'!B5,2))+1,1)-1-F30) | J30: =IF(OR(A30<> '控制台'!B4,B30<> '控制台'!B5,G30=""),"",MAX(0,DATE(VALUE(LEFT('控制台'!B5,4)),VALUE(RIGHT('控制台'!B5,2))+1,1)-1-G30)) | K30: =IF(A30="","",IF(AND(AND('控制台'!B4<>"",'控制台'!B5<>"",'控制台'!B4='刷新信息'!B6,'控制台'!B5='刷新信息'!B8),A30='控制台'!B4,B30='控制台'!B5,OR(C30="应收",C30="应付"),COUNTIFS('往来余额'!A5:A6000,C30,'往来余额'!B5:B6000,D30)=1,E30<>"",COUNTIFS(A$5:A$504,A30,B$5:B$504,B30,C$5:C$504,C30,D$5:D$504,D30,E$5:E$504,E30)=1,ISNUMBER(F30),I30>=0,ISNUMBER(H30),H30>=0),"纳入","待核实"))
I31: =IF(OR(A31<> '控制台'!B4,B31<> '控制台'!B5,F31=""),"",DATE(VALUE(LEFT('控制台'!B5,4)),VALUE(RIGHT('控制台'!B5,2))+1,1)-1-F31) | J31: =IF(OR(A31<> '控制台'!B4,B31<> '控制台'!B5,G31=""),"",MAX(0,DATE(VALUE(LEFT('控制台'!B5,4)),VALUE(RIGHT('控制台'!B5,2))+1,1)-1-G31)) | K31: =IF(A31="","",IF(AND(AND('控制台'!B4<>"",'控制台'!B5<>"",'控制台'!B4='刷新信息'!B6,'控制台'!B5='刷新信息'!B8),A31='控制台'!B4,B31='控制台'!B5,OR(C31="应收",C31="应付"),COUNTIFS('往来余额'!A5:A6000,C31,'往来余额'!B5:B6000,D31)=1,E31<>"",COUNTIFS(A$5:A$504,A31,B$5:B$504,B31,C$5:C$504,C31,D$5:D$504,D31,E$5:E$504,E31)=1,ISNUMBER(F31),I31>=0,ISNUMBER(H31),H31>=0),"纳入","待核实"))
I32: =IF(OR(A32<> '控制台'!B4,B32<> '控制台'!B5,F32=""),"",DATE(VALUE(LEFT('控制台'!B5,4)),VALUE(RIGHT('控制台'!B5,2))+1,1)-1-F32) | J32: =IF(OR(A32<> '控制台'!B4,B32<> '控制台'!B5,G32=""),"",MAX(0,DATE(VALUE(LEFT('控制台'!B5,4)),VALUE(RIGHT('控制台'!B5,2))+1,1)-1-G32)) | K32: =IF(A32="","",IF(AND(AND('控制台'!B4<>"",'控制台'!B5<>"",'控制台'!B4='刷新信息'!B6,'控制台'!B5='刷新信息'!B8),A32='控制台'!B4,B32='控制台'!B5,OR(C32="应收",C32="应付"),COUNTIFS('往来余额'!A5:A6000,C32,'往来余额'!B5:B6000,D32)=1,E32<>"",COUNTIFS(A$5:A$504,A32,B$5:B$504,B32,C$5:C$504,C32,D$5:D$504,D32,E$5:E$504,E32)=1,ISNUMBER(F32),I32>=0,ISNUMBER(H32),H32>=0),"纳入","待核实"))
I33: =IF(OR(A33<> '控制台'!B4,B33<> '控制台'!B5,F33=""),"",DATE(VALUE(LEFT('控制台'!B5,4)),VALUE(RIGHT('控制台'!B5,2))+1,1)-1-F33) | J33: =IF(OR(A33<> '控制台'!B4,B33<> '控制台'!B5,G33=""),"",MAX(0,DATE(VALUE(LEFT('控制台'!B5,4)),VALUE(RIGHT('控制台'!B5,2))+1,1)-1-G33)) | K33: =IF(A33="","",IF(AND(AND('控制台'!B4<>"",'控制台'!B5<>"",'控制台'!B4='刷新信息'!B6,'控制台'!B5='刷新信息'!B8),A33='控制台'!B4,B33='控制台'!B5,OR(C33="应收",C33="应付"),COUNTIFS('往来余额'!A5:A6000,C33,'往来余额'!B5:B6000,D33)=1,E33<>"",COUNTIFS(A$5:A$504,A33,B$5:B$504,B33,C$5:C$504,C33,D$5:D$504,D33,E$5:E$504,E33)=1,ISNUMBER(F33),I33>=0,ISNUMBER(H33),H33>=0),"纳入","待核实"))
I34: =IF(OR(A34<> '控制台'!B4,B34<> '控制台'!B5,F34=""),"",DATE(VALUE(LEFT('控制台'!B5,4)),VALUE(RIGHT('控制台'!B5,2))+1,1)-1-F34) | J34: =IF(OR(A34<> '控制台'!B4,B34<> '控制台'!B5,G34=""),"",MAX(0,DATE(VALUE(LEFT('控制台'!B5,4)),VALUE(RIGHT('控制台'!B5,2))+1,1)-1-G34)) | K34: =IF(A34="","",IF(AND(AND('控制台'!B4<>"",'控制台'!B5<>"",'控制台'!B4='刷新信息'!B6,'控制台'!B5='刷新信息'!B8),A34='控制台'!B4,B34='控制台'!B5,OR(C34="应收",C34="应付"),COUNTIFS('往来余额'!A5:A6000,C34,'往来余额'!B5:B6000,D34)=1,E34<>"",COUNTIFS(A$5:A$504,A34,B$5:B$504,B34,C$5:C$504,C34,D$5:D$504,D34,E$5:E$504,E34)=1,ISNUMBER(F34),I34>=0,ISNUMBER(H34),H34>=0),"纳入","待核实"))
I35: =IF(OR(A35<> '控制台'!B4,B35<> '控制台'!B5,F35=""),"",DATE(VALUE(LEFT('控制台'!B5,4)),VALUE(RIGHT('控制台'!B5,2))+1,1)-1-F35) | J35: =IF(OR(A35<> '控制台'!B4,B35<> '控制台'!B5,G35=""),"",MAX(0,DATE(VALUE(LEFT('控制台'!B5,4)),VALUE(RIGHT('控制台'!B5,2))+1,1)-1-G35)) | K35: =IF(A35="","",IF(AND(AND('控制台'!B4<>"",'控制台'!B5<>"",'控制台'!B4='刷新信息'!B6,'控制台'!B5='刷新信息'!B8),A35='控制台'!B4,B35='控制台'!B5,OR(C35="应收",C35="应付"),COUNTIFS('往来余额'!A5:A6000,C35,'往来余额'!B5:B6000,D35)=1,E35<>"",COUNTIFS(A$5:A$504,A35,B$5:B$504,B35,C$5:C$504,C35,D$5:D$504,D35,E$5:E$504,E35)=1,ISNUMBER(F35),I35>=0,ISNUMBER(H35),H35>=0),"纳入","待核实"))
I36: =IF(OR(A36<> '控制台'!B4,B36<> '控制台'!B5,F36=""),"",DATE(VALUE(LEFT('控制台'!B5,4)),VALUE(RIGHT('控制台'!B5,2))+1,1)-1-F36) | J36: =IF(OR(A36<> '控制台'!B4,B36<> '控制台'!B5,G36=""),"",MAX(0,DATE(VALUE(LEFT('控制台'!B5,4)),VALUE(RIGHT('控制台'!B5,2))+1,1)-1-G36)) | K36: =IF(A36="","",IF(AND(AND('控制台'!B4<>"",'控制台'!B5<>"",'控制台'!B4='刷新信息'!B6,'控制台'!B5='刷新信息'!B8),A36='控制台'!B4,B36='控制台'!B5,OR(C36="应收",C36="应付"),COUNTIFS('往来余额'!A5:A6000,C36,'往来余额'!B5:B6000,D36)=1,E36<>"",COUNTIFS(A$5:A$504,A36,B$5:B$504,B36,C$5:C$504,C36,D$5:D$504,D36,E$5:E$504,E36)=1,ISNUMBER(F36),I36>=0,ISNUMBER(H36),H36>=0),"纳入","待核实"))
I37: =IF(OR(A37<> '控制台'!B4,B37<> '控制台'!B5,F37=""),"",DATE(VALUE(LEFT('控制台'!B5,4)),VALUE(RIGHT('控制台'!B5,2))+1,1)-1-F37) | J37: =IF(OR(A37<> '控制台'!B4,B37<> '控制台'!B5,G37=""),"",MAX(0,DATE(VALUE(LEFT('控制台'!B5,4)),VALUE(RIGHT('控制台'!B5,2))+1,1)-1-G37)) | K37: =IF(A37="","",IF(AND(AND('控制台'!B4<>"",'控制台'!B5<>"",'控制台'!B4='刷新信息'!B6,'控制台'!B5='刷新信息'!B8),A37='控制台'!B4,B37='控制台'!B5,OR(C37="应收",C37="应付"),COUNTIFS('往来余额'!A5:A6000,C37,'往来余额'!B5:B6000,D37)=1,E37<>"",COUNTIFS(A$5:A$504,A37,B$5:B$504,B37,C$5:C$504,C37,D$5:D$504,D37,E$5:E$504,E37)=1,ISNUMBER(F37),I37>=0,ISNUMBER(H37),H37>=0),"纳入","待核实"))
I38: =IF(OR(A38<> '控制台'!B4,B38<> '控制台'!B5,F38=""),"",DATE(VALUE(LEFT('控制台'!B5,4)),VALUE(RIGHT('控制台'!B5,2))+1,1)-1-F38) | J38: =IF(OR(A38<> '控制台'!B4,B38<> '控制台'!B5,G38=""),"",MAX(0,DATE(VALUE(LEFT('控制台'!B5,4)),VALUE(RIGHT('控制台'!B5,2))+1,1)-1-G38)) | K38: =IF(A38="","",IF(AND(AND('控制台'!B4<>"",'控制台'!B5<>"",'控制台'!B4='刷新信息'!B6,'控制台'!B5='刷新信息'!B8),A38='控制台'!B4,B38='控制台'!B5,OR(C38="应收",C38="应付"),COUNTIFS('往来余额'!A5:A6000,C38,'往来余额'!B5:B6000,D38)=1,E38<>"",COUNTIFS(A$5:A$504,A38,B$5:B$504,B38,C$5:C$504,C38,D$5:D$504,D38,E$5:E$504,E38)=1,ISNUMBER(F38),I38>=0,ISNUMBER(H38),H38>=0),"纳入","待核实"))
I39: =IF(OR(A39<> '控制台'!B4,B39<> '控制台'!B5,F39=""),"",DATE(VALUE(LEFT('控制台'!B5,4)),VALUE(RIGHT('控制台'!B5,2))+1,1)-1-F39) | J39: =IF(OR(A39<> '控制台'!B4,B39<> '控制台'!B5,G39=""),"",MAX(0,DATE(VALUE(LEFT('控制台'!B5,4)),VALUE(RIGHT('控制台'!B5,2))+1,1)-1-G39)) | K39: =IF(A39="","",IF(AND(AND('控制台'!B4<>"",'控制台'!B5<>"",'控制台'!B4='刷新信息'!B6,'控制台'!B5='刷新信息'!B8),A39='控制台'!B4,B39='控制台'!B5,OR(C39="应收",C39="应付"),COUNTIFS('往来余额'!A5:A6000,C39,'往来余额'!B5:B6000,D39)=1,E39<>"",COUNTIFS(A$5:A$504,A39,B$5:B$504,B39,C$5:C$504,C39,D$5:D$504,D39,E$5:E$504,E39)=1,ISNUMBER(F39),I39>=0,ISNUMBER(H39),H39>=0),"纳入","待核实"))
I40: =IF(OR(A40<> '控制台'!B4,B40<> '控制台'!B5,F40=""),"",DATE(VALUE(LEFT('控制台'!B5,4)),VALUE(RIGHT('控制台'!B5,2))+1,1)-1-F40) | J40: =IF(OR(A40<> '控制台'!B4,B40<> '控制台'!B5,G40=""),"",MAX(0,DATE(VALUE(LEFT('控制台'!B5,4)),VALUE(RIGHT('控制台'!B5,2))+1,1)-1-G40)) | K40: =IF(A40="","",IF(AND(AND('控制台'!B4<>"",'控制台'!B5<>"",'控制台'!B4='刷新信息'!B6,'控制台'!B5='刷新信息'!B8),A40='控制台'!B4,B40='控制台'!B5,OR(C40="应收",C40="应付"),COUNTIFS('往来余额'!A5:A6000,C40,'往来余额'!B5:B6000,D40)=1,E40<>"",COUNTIFS(A$5:A$504,A40,B$5:B$504,B40,C$5:C$504,C40,D$5:D$504,D40,E$5:E$504,E40)=1,ISNUMBER(F40),I40>=0,ISNUMBER(H40),H40>=0),"纳入","待核实"))
I41: =IF(OR(A41<> '控制台'!B4,B41<> '控制台'!B5,F41=""),"",DATE(VALUE(LEFT('控制台'!B5,4)),VALUE(RIGHT('控制台'!B5,2))+1,1)-1-F41) | J41: =IF(OR(A41<> '控制台'!B4,B41<> '控制台'!B5,G41=""),"",MAX(0,DATE(VALUE(LEFT('控制台'!B5,4)),VALUE(RIGHT('控制台'!B5,2))+1,1)-1-G41)) | K41: =IF(A41="","",IF(AND(AND('控制台'!B4<>"",'控制台'!B5<>"",'控制台'!B4='刷新信息'!B6,'控制台'!B5='刷新信息'!B8),A41='控制台'!B4,B41='控制台'!B5,OR(C41="应收",C41="应付"),COUNTIFS('往来余额'!A5:A6000,C41,'往来余额'!B5:B6000,D41)=1,E41<>"",COUNTIFS(A$5:A$504,A41,B$5:B$504,B41,C$5:C$504,C41,D$5:D$504,D41,E$5:E$504,E41)=1,ISNUMBER(F41),I41>=0,ISNUMBER(H41),H41>=0),"纳入","待核实"))
I42: =IF(OR(A42<> '控制台'!B4,B42<> '控制台'!B5,F42=""),"",DATE(VALUE(LEFT('控制台'!B5,4)),VALUE(RIGHT('控制台'!B5,2))+1,1)-1-F42) | J42: =IF(OR(A42<> '控制台'!B4,B42<> '控制台'!B5,G42=""),"",MAX(0,DATE(VALUE(LEFT('控制台'!B5,4)),VALUE(RIGHT('控制台'!B5,2))+1,1)-1-G42)) | K42: =IF(A42="","",IF(AND(AND('控制台'!B4<>"",'控制台'!B5<>"",'控制台'!B4='刷新信息'!B6,'控制台'!B5='刷新信息'!B8),A42='控制台'!B4,B42='控制台'!B5,OR(C42="应收",C42="应付"),COUNTIFS('往来余额'!A5:A6000,C42,'往来余额'!B5:B6000,D42)=1,E42<>"",COUNTIFS(A$5:A$504,A42,B$5:B$504,B42,C$5:C$504,C42,D$5:D$504,D42,E$5:E$504,E42)=1,ISNUMBER(F42),I42>=0,ISNUMBER(H42),H42>=0),"纳入","待核实"))
I43: =IF(OR(A43<> '控制台'!B4,B43<> '控制台'!B5,F43=""),"",DATE(VALUE(LEFT('控制台'!B5,4)),VALUE(RIGHT('控制台'!B5,2))+1,1)-1-F43) | J43: =IF(OR(A43<> '控制台'!B4,B43<> '控制台'!B5,G43=""),"",MAX(0,DATE(VALUE(LEFT('控制台'!B5,4)),VALUE(RIGHT('控制台'!B5,2))+1,1)-1-G43)) | K43: =IF(A43="","",IF(AND(AND('控制台'!B4<>"",'控制台'!B5<>"",'控制台'!B4='刷新信息'!B6,'控制台'!B5='刷新信息'!B8),A43='控制台'!B4,B43='控制台'!B5,OR(C43="应收",C43="应付"),COUNTIFS('往来余额'!A5:A6000,C43,'往来余额'!B5:B6000,D43)=1,E43<>"",COUNTIFS(A$5:A$504,A43,B$5:B$504,B43,C$5:C$504,C43,D$5:D$504,D43,E$5:E$504,E43)=1,ISNUMBER(F43),I43>=0,ISNUMBER(H43),H43>=0),"纳入","待核实"))
I44: =IF(OR(A44<> '控制台'!B4,B44<> '控制台'!B5,F44=""),"",DATE(VALUE(LEFT('控制台'!B5,4)),VALUE(RIGHT('控制台'!B5,2))+1,1)-1-F44) | J44: =IF(OR(A44<> '控制台'!B4,B44<> '控制台'!B5,G44=""),"",MAX(0,DATE(VALUE(LEFT('控制台'!B5,4)),VALUE(RIGHT('控制台'!B5,2))+1,1)-1-G44)) | K44: =IF(A44="","",IF(AND(AND('控制台'!B4<>"",'控制台'!B5<>"",'控制台'!B4='刷新信息'!B6,'控制台'!B5='刷新信息'!B8),A44='控制台'!B4,B44='控制台'!B5,OR(C44="应收",C44="应付"),COUNTIFS('往来余额'!A5:A6000,C44,'往来余额'!B5:B6000,D44)=1,E44<>"",COUNTIFS(A$5:A$504,A44,B$5:B$504,B44,C$5:C$504,C44,D$5:D$504,D44,E$5:E$504,E44)=1,ISNUMBER(F44),I44>=0,ISNUMBER(H44),H44>=0),"纳入","待核实"))
I45: =IF(OR(A45<> '控制台'!B4,B45<> '控制台'!B5,F45=""),"",DATE(VALUE(LEFT('控制台'!B5,4)),VALUE(RIGHT('控制台'!B5,2))+1,1)-1-F45) | J45: =IF(OR(A45<> '控制台'!B4,B45<> '控制台'!B5,G45=""),"",MAX(0,DATE(VALUE(LEFT('控制台'!B5,4)),VALUE(RIGHT('控制台'!B5,2))+1,1)-1-G45)) | K45: =IF(A45="","",IF(AND(AND('控制台'!B4<>"",'控制台'!B5<>"",'控制台'!B4='刷新信息'!B6,'控制台'!B5='刷新信息'!B8),A45='控制台'!B4,B45='控制台'!B5,OR(C45="应收",C45="应付"),COUNTIFS('往来余额'!A5:A6000,C45,'往来余额'!B5:B6000,D45)=1,E45<>"",COUNTIFS(A$5:A$504,A45,B$5:B$504,B45,C$5:C$504,C45,D$5:D$504,D45,E$5:E$504,E45)=1,ISNUMBER(F45),I45>=0,ISNUMBER(H45),H45>=0),"纳入","待核实"))
I46: =IF(OR(A46<> '控制台'!B4,B46<> '控制台'!B5,F46=""),"",DATE(VALUE(LEFT('控制台'!B5,4)),VALUE(RIGHT('控制台'!B5,2))+1,1)-1-F46) | J46: =IF(OR(A46<> '控制台'!B4,B46<> '控制台'!B5,G46=""),"",MAX(0,DATE(VALUE(LEFT('控制台'!B5,4)),VALUE(RIGHT('控制台'!B5,2))+1,1)-1-G46)) | K46: =IF(A46="","",IF(AND(AND('控制台'!B4<>"",'控制台'!B5<>"",'控制台'!B4='刷新信息'!B6,'控制台'!B5='刷新信息'!B8),A46='控制台'!B4,B46='控制台'!B5,OR(C46="应收",C46="应付"),COUNTIFS('往来余额'!A5:A6000,C46,'往来余额'!B5:B6000,D46)=1,E46<>"",COUNTIFS(A$5:A$504,A46,B$5:B$504,B46,C$5:C$504,C46,D$5:D$504,D46,E$5:E$504,E46)=1,ISNUMBER(F46),I46>=0,ISNUMBER(H46),H46>=0),"纳入","待核实"))
I47: =IF(OR(A47<> '控制台'!B4,B47<> '控制台'!B5,F47=""),"",DATE(VALUE(LEFT('控制台'!B5,4)),VALUE(RIGHT('控制台'!B5,2))+1,1)-1-F47) | J47: =IF(OR(A47<> '控制台'!B4,B47<> '控制台'!B5,G47=""),"",MAX(0,DATE(VALUE(LEFT('控制台'!B5,4)),VALUE(RIGHT('控制台'!B5,2))+1,1)-1-G47)) | K47: =IF(A47="","",IF(AND(AND('控制台'!B4<>"",'控制台'!B5<>"",'控制台'!B4='刷新信息'!B6,'控制台'!B5='刷新信息'!B8),A47='控制台'!B4,B47='控制台'!B5,OR(C47="应收",C47="应付"),COUNTIFS('往来余额'!A5:A6000,C47,'往来余额'!B5:B6000,D47)=1,E47<>"",COUNTIFS(A$5:A$504,A47,B$5:B$504,B47,C$5:C$504,C47,D$5:D$504,D47,E$5:E$504,E47)=1,ISNUMBER(F47),I47>=0,ISNUMBER(H47),H47>=0),"纳入","待核实"))
I48: =IF(OR(A48<> '控制台'!B4,B48<> '控制台'!B5,F48=""),"",DATE(VALUE(LEFT('控制台'!B5,4)),VALUE(RIGHT('控制台'!B5,2))+1,1)-1-F48) | J48: =IF(OR(A48<> '控制台'!B4,B48<> '控制台'!B5,G48=""),"",MAX(0,DATE(VALUE(LEFT('控制台'!B5,4)),VALUE(RIGHT('控制台'!B5,2))+1,1)-1-G48)) | K48: =IF(A48="","",IF(AND(AND('控制台'!B4<>"",'控制台'!B5<>"",'控制台'!B4='刷新信息'!B6,'控制台'!B5='刷新信息'!B8),A48='控制台'!B4,B48='控制台'!B5,OR(C48="应收",C48="应付"),COUNTIFS('往来余额'!A5:A6000,C48,'往来余额'!B5:B6000,D48)=1,E48<>"",COUNTIFS(A$5:A$504,A48,B$5:B$504,B48,C$5:C$504,C48,D$5:D$504,D48,E$5:E$504,E48)=1,ISNUMBER(F48),I48>=0,ISNUMBER(H48),H48>=0),"纳入","待核实"))
I49: =IF(OR(A49<> '控制台'!B4,B49<> '控制台'!B5,F49=""),"",DATE(VALUE(LEFT('控制台'!B5,4)),VALUE(RIGHT('控制台'!B5,2))+1,1)-1-F49) | J49: =IF(OR(A49<> '控制台'!B4,B49<> '控制台'!B5,G49=""),"",MAX(0,DATE(VALUE(LEFT('控制台'!B5,4)),VALUE(RIGHT('控制台'!B5,2))+1,1)-1-G49)) | K49: =IF(A49="","",IF(AND(AND('控制台'!B4<>"",'控制台'!B5<>"",'控制台'!B4='刷新信息'!B6,'控制台'!B5='刷新信息'!B8),A49='控制台'!B4,B49='控制台'!B5,OR(C49="应收",C49="应付"),COUNTIFS('往来余额'!A5:A6000,C49,'往来余额'!B5:B6000,D49)=1,E49<>"",COUNTIFS(A$5:A$504,A49,B$5:B$504,B49,C$5:C$504,C49,D$5:D$504,D49,E$5:E$504,E49)=1,ISNUMBER(F49),I49>=0,ISNUMBER(H49),H49>=0),"纳入","待核实"))
I50: =IF(OR(A50<> '控制台'!B4,B50<> '控制台'!B5,F50=""),"",DATE(VALUE(LEFT('控制台'!B5,4)),VALUE(RIGHT('控制台'!B5,2))+1,1)-1-F50) | J50: =IF(OR(A50<> '控制台'!B4,B50<> '控制台'!B5,G50=""),"",MAX(0,DATE(VALUE(LEFT('控制台'!B5,4)),VALUE(RIGHT('控制台'!B5,2))+1,1)-1-G50)) | K50: =IF(A50="","",IF(AND(AND('控制台'!B4<>"",'控制台'!B5<>"",'控制台'!B4='刷新信息'!B6,'控制台'!B5='刷新信息'!B8),A50='控制台'!B4,B50='控制台'!B5,OR(C50="应收",C50="应付"),COUNTIFS('往来余额'!A5:A6000,C50,'往来余额'!B5:B6000,D50)=1,E50<>"",COUNTIFS(A$5:A$504,A50,B$5:B$504,B50,C$5:C$504,C50,D$5:D$504,D50,E$5:E$504,E50)=1,ISNUMBER(F50),I50>=0,ISNUMBER(H50),H50>=0),"纳入","待核实"))
I51: =IF(OR(A51<> '控制台'!B4,B51<> '控制台'!B5,F51=""),"",DATE(VALUE(LEFT('控制台'!B5,4)),VALUE(RIGHT('控制台'!B5,2))+1,1)-1-F51) | J51: =IF(OR(A51<> '控制台'!B4,B51<> '控制台'!B5,G51=""),"",MAX(0,DATE(VALUE(LEFT('控制台'!B5,4)),VALUE(RIGHT('控制台'!B5,2))+1,1)-1-G51)) | K51: =IF(A51="","",IF(AND(AND('控制台'!B4<>"",'控制台'!B5<>"",'控制台'!B4='刷新信息'!B6,'控制台'!B5='刷新信息'!B8),A51='控制台'!B4,B51='控制台'!B5,OR(C51="应收",C51="应付"),COUNTIFS('往来余额'!A5:A6000,C51,'往来余额'!B5:B6000,D51)=1,E51<>"",COUNTIFS(A$5:A$504,A51,B$5:B$504,B51,C$5:C$504,C51,D$5:D$504,D51,E$5:E$504,E51)=1,ISNUMBER(F51),I51>=0,ISNUMBER(H51),H51>=0),"纳入","待核实"))
I52: =IF(OR(A52<> '控制台'!B4,B52<> '控制台'!B5,F52=""),"",DATE(VALUE(LEFT('控制台'!B5,4)),VALUE(RIGHT('控制台'!B5,2))+1,1)-1-F52) | J52: =IF(OR(A52<> '控制台'!B4,B52<> '控制台'!B5,G52=""),"",MAX(0,DATE(VALUE(LEFT('控制台'!B5,4)),VALUE(RIGHT('控制台'!B5,2))+1,1)-1-G52)) | K52: =IF(A52="","",IF(AND(AND('控制台'!B4<>"",'控制台'!B5<>"",'控制台'!B4='刷新信息'!B6,'控制台'!B5='刷新信息'!B8),A52='控制台'!B4,B52='控制台'!B5,OR(C52="应收",C52="应付"),COUNTIFS('往来余额'!A5:A6000,C52,'往来余额'!B5:B6000,D52)=1,E52<>"",COUNTIFS(A$5:A$504,A52,B$5:B$504,B52,C$5:C$504,C52,D$5:D$504,D52,E$5:E$504,E52)=1,ISNUMBER(F52),I52>=0,ISNUMBER(H52),H52>=0),"纳入","待核实"))
I53: =IF(OR(A53<> '控制台'!B4,B53<> '控制台'!B5,F53=""),"",DATE(VALUE(LEFT('控制台'!B5,4)),VALUE(RIGHT('控制台'!B5,2))+1,1)-1-F53) | J53: =IF(OR(A53<> '控制台'!B4,B53<> '控制台'!B5,G53=""),"",MAX(0,DATE(VALUE(LEFT('控制台'!B5,4)),VALUE(RIGHT('控制台'!B5,2))+1,1)-1-G53)) | K53: =IF(A53="","",IF(AND(AND('控制台'!B4<>"",'控制台'!B5<>"",'控制台'!B4='刷新信息'!B6,'控制台'!B5='刷新信息'!B8),A53='控制台'!B4,B53='控制台'!B5,OR(C53="应收",C53="应付"),COUNTIFS('往来余额'!A5:A6000,C53,'往来余额'!B5:B6000,D53)=1,E53<>"",COUNTIFS(A$5:A$504,A53,B$5:B$504,B53,C$5:C$504,C53,D$5:D$504,D53,E$5:E$504,E53)=1,ISNUMBER(F53),I53>=0,ISNUMBER(H53),H53>=0),"纳入","待核实"))
I54: =IF(OR(A54<> '控制台'!B4,B54<> '控制台'!B5,F54=""),"",DATE(VALUE(LEFT('控制台'!B5,4)),VALUE(RIGHT('控制台'!B5,2))+1,1)-1-F54) | J54: =IF(OR(A54<> '控制台'!B4,B54<> '控制台'!B5,G54=""),"",MAX(0,DATE(VALUE(LEFT('控制台'!B5,4)),VALUE(RIGHT('控制台'!B5,2))+1,1)-1-G54)) | K54: =IF(A54="","",IF(AND(AND('控制台'!B4<>"",'控制台'!B5<>"",'控制台'!B4='刷新信息'!B6,'控制台'!B5='刷新信息'!B8),A54='控制台'!B4,B54='控制台'!B5,OR(C54="应收",C54="应付"),COUNTIFS('往来余额'!A5:A6000,C54,'往来余额'!B5:B6000,D54)=1,E54<>"",COUNTIFS(A$5:A$504,A54,B$5:B$504,B54,C$5:C$504,C54,D$5:D$504,D54,E$5:E$504,E54)=1,ISNUMBER(F54),I54>=0,ISNUMBER(H54),H54>=0),"纳入","待核实"))
I55: =IF(OR(A55<> '控制台'!B4,B55<> '控制台'!B5,F55=""),"",DATE(VALUE(LEFT('控制台'!B5,4)),VALUE(RIGHT('控制台'!B5,2))+1,1)-1-F55) | J55: =IF(OR(A55<> '控制台'!B4,B55<> '控制台'!B5,G55=""),"",MAX(0,DATE(VALUE(LEFT('控制台'!B5,4)),VALUE(RIGHT('控制台'!B5,2))+1,1)-1-G55)) | K55: =IF(A55="","",IF(AND(AND('控制台'!B4<>"",'控制台'!B5<>"",'控制台'!B4='刷新信息'!B6,'控制台'!B5='刷新信息'!B8),A55='控制台'!B4,B55='控制台'!B5,OR(C55="应收",C55="应付"),COUNTIFS('往来余额'!A5:A6000,C55,'往来余额'!B5:B6000,D55)=1,E55<>"",COUNTIFS(A$5:A$504,A55,B$5:B$504,B55,C$5:C$504,C55,D$5:D$504,D55,E$5:E$504,E55)=1,ISNUMBER(F55),I55>=0,ISNUMBER(H55),H55>=0),"纳入","待核实"))
I56: =IF(OR(A56<> '控制台'!B4,B56<> '控制台'!B5,F56=""),"",DATE(VALUE(LEFT('控制台'!B5,4)),VALUE(RIGHT('控制台'!B5,2))+1,1)-1-F56) | J56: =IF(OR(A56<> '控制台'!B4,B56<> '控制台'!B5,G56=""),"",MAX(0,DATE(VALUE(LEFT('控制台'!B5,4)),VALUE(RIGHT('控制台'!B5,2))+1,1)-1-G56)) | K56: =IF(A56="","",IF(AND(AND('控制台'!B4<>"",'控制台'!B5<>"",'控制台'!B4='刷新信息'!B6,'控制台'!B5='刷新信息'!B8),A56='控制台'!B4,B56='控制台'!B5,OR(C56="应收",C56="应付"),COUNTIFS('往来余额'!A5:A6000,C56,'往来余额'!B5:B6000,D56)=1,E56<>"",COUNTIFS(A$5:A$504,A56,B$5:B$504,B56,C$5:C$504,C56,D$5:D$504,D56,E$5:E$504,E56)=1,ISNUMBER(F56),I56>=0,ISNUMBER(H56),H56>=0),"纳入","待核实"))
I57: =IF(OR(A57<> '控制台'!B4,B57<> '控制台'!B5,F57=""),"",DATE(VALUE(LEFT('控制台'!B5,4)),VALUE(RIGHT('控制台'!B5,2))+1,1)-1-F57) | J57: =IF(OR(A57<> '控制台'!B4,B57<> '控制台'!B5,G57=""),"",MAX(0,DATE(VALUE(LEFT('控制台'!B5,4)),VALUE(RIGHT('控制台'!B5,2))+1,1)-1-G57)) | K57: =IF(A57="","",IF(AND(AND('控制台'!B4<>"",'控制台'!B5<>"",'控制台'!B4='刷新信息'!B6,'控制台'!B5='刷新信息'!B8),A57='控制台'!B4,B57='控制台'!B5,OR(C57="应收",C57="应付"),COUNTIFS('往来余额'!A5:A6000,C57,'往来余额'!B5:B6000,D57)=1,E57<>"",COUNTIFS(A$5:A$504,A57,B$5:B$504,B57,C$5:C$504,C57,D$5:D$504,D57,E$5:E$504,E57)=1,ISNUMBER(F57),I57>=0,ISNUMBER(H57),H57>=0),"纳入","待核实"))
I58: =IF(OR(A58<> '控制台'!B4,B58<> '控制台'!B5,F58=""),"",DATE(VALUE(LEFT('控制台'!B5,4)),VALUE(RIGHT('控制台'!B5,2))+1,1)-1-F58) | J58: =IF(OR(A58<> '控制台'!B4,B58<> '控制台'!B5,G58=""),"",MAX(0,DATE(VALUE(LEFT('控制台'!B5,4)),VALUE(RIGHT('控制台'!B5,2))+1,1)-1-G58)) | K58: =IF(A58="","",IF(AND(AND('控制台'!B4<>"",'控制台'!B5<>"",'控制台'!B4='刷新信息'!B6,'控制台'!B5='刷新信息'!B8),A58='控制台'!B4,B58='控制台'!B5,OR(C58="应收",C58="应付"),COUNTIFS('往来余额'!A5:A6000,C58,'往来余额'!B5:B6000,D58)=1,E58<>"",COUNTIFS(A$5:A$504,A58,B$5:B$504,B58,C$5:C$504,C58,D$5:D$504,D58,E$5:E$504,E58)=1,ISNUMBER(F58),I58>=0,ISNUMBER(H58),H58>=0),"纳入","待核实"))
I59: =IF(OR(A59<> '控制台'!B4,B59<> '控制台'!B5,F59=""),"",DATE(VALUE(LEFT('控制台'!B5,4)),VALUE(RIGHT('控制台'!B5,2))+1,1)-1-F59) | J59: =IF(OR(A59<> '控制台'!B4,B59<> '控制台'!B5,G59=""),"",MAX(0,DATE(VALUE(LEFT('控制台'!B5,4)),VALUE(RIGHT('控制台'!B5,2))+1,1)-1-G59)) | K59: =IF(A59="","",IF(AND(AND('控制台'!B4<>"",'控制台'!B5<>"",'控制台'!B4='刷新信息'!B6,'控制台'!B5='刷新信息'!B8),A59='控制台'!B4,B59='控制台'!B5,OR(C59="应收",C59="应付"),COUNTIFS('往来余额'!A5:A6000,C59,'往来余额'!B5:B6000,D59)=1,E59<>"",COUNTIFS(A$5:A$504,A59,B$5:B$504,B59,C$5:C$504,C59,D$5:D$504,D59,E$5:E$504,E59)=1,ISNUMBER(F59),I59>=0,ISNUMBER(H59),H59>=0),"纳入","待核实"))
I60: =IF(OR(A60<> '控制台'!B4,B60<> '控制台'!B5,F60=""),"",DATE(VALUE(LEFT('控制台'!B5,4)),VALUE(RIGHT('控制台'!B5,2))+1,1)-1-F60) | J60: =IF(OR(A60<> '控制台'!B4,B60<> '控制台'!B5,G60=""),"",MAX(0,DATE(VALUE(LEFT('控制台'!B5,4)),VALUE(RIGHT('控制台'!B5,2))+1,1)-1-G60)) | K60: =IF(A60="","",IF(AND(AND('控制台'!B4<>"",'控制台'!B5<>"",'控制台'!B4='刷新信息'!B6,'控制台'!B5='刷新信息'!B8),A60='控制台'!B4,B60='控制台'!B5,OR(C60="应收",C60="应付"),COUNTIFS('往来余额'!A5:A6000,C60,'往来余额'!B5:B6000,D60)=1,E60<>"",COUNTIFS(A$5:A$504,A60,B$5:B$504,B60,C$5:C$504,C60,D$5:D$504,D60,E$5:E$504,E60)=1,ISNUMBER(F60),I60>=0,ISNUMBER(H60),H60>=0),"纳入","待核实"))
I61: =IF(OR(A61<> '控制台'!B4,B61<> '控制台'!B5,F61=""),"",DATE(VALUE(LEFT('控制台'!B5,4)),VALUE(RIGHT('控制台'!B5,2))+1,1)-1-F61) | J61: =IF(OR(A61<> '控制台'!B4,B61<> '控制台'!B5,G61=""),"",MAX(0,DATE(VALUE(LEFT('控制台'!B5,4)),VALUE(RIGHT('控制台'!B5,2))+1,1)-1-G61)) | K61: =IF(A61="","",IF(AND(AND('控制台'!B4<>"",'控制台'!B5<>"",'控制台'!B4='刷新信息'!B6,'控制台'!B5='刷新信息'!B8),A61='控制台'!B4,B61='控制台'!B5,OR(C61="应收",C61="应付"),COUNTIFS('往来余额'!A5:A6000,C61,'往来余额'!B5:B6000,D61)=1,E61<>"",COUNTIFS(A$5:A$504,A61,B$5:B$504,B61,C$5:C$504,C61,D$5:D$504,D61,E$5:E$504,E61)=1,ISNUMBER(F61),I61>=0,ISNUMBER(H61),H61>=0),"纳入","待核实"))
I62: =IF(OR(A62<> '控制台'!B4,B62<> '控制台'!B5,F62=""),"",DATE(VALUE(LEFT('控制台'!B5,4)),VALUE(RIGHT('控制台'!B5,2))+1,1)-1-F62) | J62: =IF(OR(A62<> '控制台'!B4,B62<> '控制台'!B5,G62=""),"",MAX(0,DATE(VALUE(LEFT('控制台'!B5,4)),VALUE(RIGHT('控制台'!B5,2))+1,1)-1-G62)) | K62: =IF(A62="","",IF(AND(AND('控制台'!B4<>"",'控制台'!B5<>"",'控制台'!B4='刷新信息'!B6,'控制台'!B5='刷新信息'!B8),A62='控制台'!B4,B62='控制台'!B5,OR(C62="应收",C62="应付"),COUNTIFS('往来余额'!A5:A6000,C62,'往来余额'!B5:B6000,D62)=1,E62<>"",COUNTIFS(A$5:A$504,A62,B$5:B$504,B62,C$5:C$504,C62,D$5:D$504,D62,E$5:E$504,E62)=1,ISNUMBER(F62),I62>=0,ISNUMBER(H62),H62>=0),"纳入","待核实"))
I63: =IF(OR(A63<> '控制台'!B4,B63<> '控制台'!B5,F63=""),"",DATE(VALUE(LEFT('控制台'!B5,4)),VALUE(RIGHT('控制台'!B5,2))+1,1)-1-F63) | J63: =IF(OR(A63<> '控制台'!B4,B63<> '控制台'!B5,G63=""),"",MAX(0,DATE(VALUE(LEFT('控制台'!B5,4)),VALUE(RIGHT('控制台'!B5,2))+1,1)-1-G63)) | K63: =IF(A63="","",IF(AND(AND('控制台'!B4<>"",'控制台'!B5<>"",'控制台'!B4='刷新信息'!B6,'控制台'!B5='刷新信息'!B8),A63='控制台'!B4,B63='控制台'!B5,OR(C63="应收",C63="应付"),COUNTIFS('往来余额'!A5:A6000,C63,'往来余额'!B5:B6000,D63)=1,E63<>"",COUNTIFS(A$5:A$504,A63,B$5:B$504,B63,C$5:C$504,C63,D$5:D$504,D63,E$5:E$504,E63)=1,ISNUMBER(F63),I63>=0,ISNUMBER(H63),H63>=0),"纳入","待核实"))
I64: =IF(OR(A64<> '控制台'!B4,B64<> '控制台'!B5,F64=""),"",DATE(VALUE(LEFT('控制台'!B5,4)),VALUE(RIGHT('控制台'!B5,2))+1,1)-1-F64) | J64: =IF(OR(A64<> '控制台'!B4,B64<> '控制台'!B5,G64=""),"",MAX(0,DATE(VALUE(LEFT('控制台'!B5,4)),VALUE(RIGHT('控制台'!B5,2))+1,1)-1-G64)) | K64: =IF(A64="","",IF(AND(AND('控制台'!B4<>"",'控制台'!B5<>"",'控制台'!B4='刷新信息'!B6,'控制台'!B5='刷新信息'!B8),A64='控制台'!B4,B64='控制台'!B5,OR(C64="应收",C64="应付"),COUNTIFS('往来余额'!A5:A6000,C64,'往来余额'!B5:B6000,D64)=1,E64<>"",COUNTIFS(A$5:A$504,A64,B$5:B$504,B64,C$5:C$504,C64,D$5:D$504,D64,E$5:E$504,E64)=1,ISNUMBER(F64),I64>=0,ISNUMBER(H64),H64>=0),"纳入","待核实"))
I65: =IF(OR(A65<> '控制台'!B4,B65<> '控制台'!B5,F65=""),"",DATE(VALUE(LEFT('控制台'!B5,4)),VALUE(RIGHT('控制台'!B5,2))+1,1)-1-F65) | J65: =IF(OR(A65<> '控制台'!B4,B65<> '控制台'!B5,G65=""),"",MAX(0,DATE(VALUE(LEFT('控制台'!B5,4)),VALUE(RIGHT('控制台'!B5,2))+1,1)-1-G65)) | K65: =IF(A65="","",IF(AND(AND('控制台'!B4<>"",'控制台'!B5<>"",'控制台'!B4='刷新信息'!B6,'控制台'!B5='刷新信息'!B8),A65='控制台'!B4,B65='控制台'!B5,OR(C65="应收",C65="应付"),COUNTIFS('往来余额'!A5:A6000,C65,'往来余额'!B5:B6000,D65)=1,E65<>"",COUNTIFS(A$5:A$504,A65,B$5:B$504,B65,C$5:C$504,C65,D$5:D$504,D65,E$5:E$504,E65)=1,ISNUMBER(F65),I65>=0,ISNUMBER(H65),H65>=0),"纳入","待核实"))
I66: =IF(OR(A66<> '控制台'!B4,B66<> '控制台'!B5,F66=""),"",DATE(VALUE(LEFT('控制台'!B5,4)),VALUE(RIGHT('控制台'!B5,2))+1,1)-1-F66) | J66: =IF(OR(A66<> '控制台'!B4,B66<> '控制台'!B5,G66=""),"",MAX(0,DATE(VALUE(LEFT('控制台'!B5,4)),VALUE(RIGHT('控制台'!B5,2))+1,1)-1-G66)) | K66: =IF(A66="","",IF(AND(AND('控制台'!B4<>"",'控制台'!B5<>"",'控制台'!B4='刷新信息'!B6,'控制台'!B5='刷新信息'!B8),A66='控制台'!B4,B66='控制台'!B5,OR(C66="应收",C66="应付"),COUNTIFS('往来余额'!A5:A6000,C66,'往来余额'!B5:B6000,D66)=1,E66<>"",COUNTIFS(A$5:A$504,A66,B$5:B$504,B66,C$5:C$504,C66,D$5:D$504,D66,E$5:E$504,E66)=1,ISNUMBER(F66),I66>=0,ISNUMBER(H66),H66>=0),"纳入","待核实"))
I67: =IF(OR(A67<> '控制台'!B4,B67<> '控制台'!B5,F67=""),"",DATE(VALUE(LEFT('控制台'!B5,4)),VALUE(RIGHT('控制台'!B5,2))+1,1)-1-F67) | J67: =IF(OR(A67<> '控制台'!B4,B67<> '控制台'!B5,G67=""),"",MAX(0,DATE(VALUE(LEFT('控制台'!B5,4)),VALUE(RIGHT('控制台'!B5,2))+1,1)-1-G67)) | K67: =IF(A67="","",IF(AND(AND('控制台'!B4<>"",'控制台'!B5<>"",'控制台'!B4='刷新信息'!B6,'控制台'!B5='刷新信息'!B8),A67='控制台'!B4,B67='控制台'!B5,OR(C67="应收",C67="应付"),COUNTIFS('往来余额'!A5:A6000,C67,'往来余额'!B5:B6000,D67)=1,E67<>"",COUNTIFS(A$5:A$504,A67,B$5:B$504,B67,C$5:C$504,C67,D$5:D$504,D67,E$5:E$504,E67)=1,ISNUMBER(F67),I67>=0,ISNUMBER(H67),H67>=0),"纳入","待核实"))
I68: =IF(OR(A68<> '控制台'!B4,B68<> '控制台'!B5,F68=""),"",DATE(VALUE(LEFT('控制台'!B5,4)),VALUE(RIGHT('控制台'!B5,2))+1,1)-1-F68) | J68: =IF(OR(A68<> '控制台'!B4,B68<> '控制台'!B5,G68=""),"",MAX(0,DATE(VALUE(LEFT('控制台'!B5,4)),VALUE(RIGHT('控制台'!B5,2))+1,1)-1-G68)) | K68: =IF(A68="","",IF(AND(AND('控制台'!B4<>"",'控制台'!B5<>"",'控制台'!B4='刷新信息'!B6,'控制台'!B5='刷新信息'!B8),A68='控制台'!B4,B68='控制台'!B5,OR(C68="应收",C68="应付"),COUNTIFS('往来余额'!A5:A6000,C68,'往来余额'!B5:B6000,D68)=1,E68<>"",COUNTIFS(A$5:A$504,A68,B$5:B$504,B68,C$5:C$504,C68,D$5:D$504,D68,E$5:E$504,E68)=1,ISNUMBER(F68),I68>=0,ISNUMBER(H68),H68>=0),"纳入","待核实"))
I69: =IF(OR(A69<> '控制台'!B4,B69<> '控制台'!B5,F69=""),"",DATE(VALUE(LEFT('控制台'!B5,4)),VALUE(RIGHT('控制台'!B5,2))+1,1)-1-F69) | J69: =IF(OR(A69<> '控制台'!B4,B69<> '控制台'!B5,G69=""),"",MAX(0,DATE(VALUE(LEFT('控制台'!B5,4)),VALUE(RIGHT('控制台'!B5,2))+1,1)-1-G69)) | K69: =IF(A69="","",IF(AND(AND('控制台'!B4<>"",'控制台'!B5<>"",'控制台'!B4='刷新信息'!B6,'控制台'!B5='刷新信息'!B8),A69='控制台'!B4,B69='控制台'!B5,OR(C69="应收",C69="应付"),COUNTIFS('往来余额'!A5:A6000,C69,'往来余额'!B5:B6000,D69)=1,E69<>"",COUNTIFS(A$5:A$504,A69,B$5:B$504,B69,C$5:C$504,C69,D$5:D$504,D69,E$5:E$504,E69)=1,ISNUMBER(F69),I69>=0,ISNUMBER(H69),H69>=0),"纳入","待核实"))
I70: =IF(OR(A70<> '控制台'!B4,B70<> '控制台'!B5,F70=""),"",DATE(VALUE(LEFT('控制台'!B5,4)),VALUE(RIGHT('控制台'!B5,2))+1,1)-1-F70) | J70: =IF(OR(A70<> '控制台'!B4,B70<> '控制台'!B5,G70=""),"",MAX(0,DATE(VALUE(LEFT('控制台'!B5,4)),VALUE(RIGHT('控制台'!B5,2))+1,1)-1-G70)) | K70: =IF(A70="","",IF(AND(AND('控制台'!B4<>"",'控制台'!B5<>"",'控制台'!B4='刷新信息'!B6,'控制台'!B5='刷新信息'!B8),A70='控制台'!B4,B70='控制台'!B5,OR(C70="应收",C70="应付"),COUNTIFS('往来余额'!A5:A6000,C70,'往来余额'!B5:B6000,D70)=1,E70<>"",COUNTIFS(A$5:A$504,A70,B$5:B$504,B70,C$5:C$504,C70,D$5:D$504,D70,E$5:E$504,E70)=1,ISNUMBER(F70),I70>=0,ISNUMBER(H70),H70>=0),"纳入","待核实"))
I71: =IF(OR(A71<> '控制台'!B4,B71<> '控制台'!B5,F71=""),"",DATE(VALUE(LEFT('控制台'!B5,4)),VALUE(RIGHT('控制台'!B5,2))+1,1)-1-F71) | J71: =IF(OR(A71<> '控制台'!B4,B71<> '控制台'!B5,G71=""),"",MAX(0,DATE(VALUE(LEFT('控制台'!B5,4)),VALUE(RIGHT('控制台'!B5,2))+1,1)-1-G71)) | K71: =IF(A71="","",IF(AND(AND('控制台'!B4<>"",'控制台'!B5<>"",'控制台'!B4='刷新信息'!B6,'控制台'!B5='刷新信息'!B8),A71='控制台'!B4,B71='控制台'!B5,OR(C71="应收",C71="应付"),COUNTIFS('往来余额'!A5:A6000,C71,'往来余额'!B5:B6000,D71)=1,E71<>"",COUNTIFS(A$5:A$504,A71,B$5:B$504,B71,C$5:C$504,C71,D$5:D$504,D71,E$5:E$504,E71)=1,ISNUMBER(F71),I71>=0,ISNUMBER(H71),H71>=0),"纳入","待核实"))
I72: =IF(OR(A72<> '控制台'!B4,B72<> '控制台'!B5,F72=""),"",DATE(VALUE(LEFT('控制台'!B5,4)),VALUE(RIGHT('控制台'!B5,2))+1,1)-1-F72) | J72: =IF(OR(A72<> '控制台'!B4,B72<> '控制台'!B5,G72=""),"",MAX(0,DATE(VALUE(LEFT('控制台'!B5,4)),VALUE(RIGHT('控制台'!B5,2))+1,1)-1-G72)) | K72: =IF(A72="","",IF(AND(AND('控制台'!B4<>"",'控制台'!B5<>"",'控制台'!B4='刷新信息'!B6,'控制台'!B5='刷新信息'!B8),A72='控制台'!B4,B72='控制台'!B5,OR(C72="应收",C72="应付"),COUNTIFS('往来余额'!A5:A6000,C72,'往来余额'!B5:B6000,D72)=1,E72<>"",COUNTIFS(A$5:A$504,A72,B$5:B$504,B72,C$5:C$504,C72,D$5:D$504,D72,E$5:E$504,E72)=1,ISNUMBER(F72),I72>=0,ISNUMBER(H72),H72>=0),"纳入","待核实"))
I73: =IF(OR(A73<> '控制台'!B4,B73<> '控制台'!B5,F73=""),"",DATE(VALUE(LEFT('控制台'!B5,4)),VALUE(RIGHT('控制台'!B5,2))+1,1)-1-F73) | J73: =IF(OR(A73<> '控制台'!B4,B73<> '控制台'!B5,G73=""),"",MAX(0,DATE(VALUE(LEFT('控制台'!B5,4)),VALUE(RIGHT('控制台'!B5,2))+1,1)-1-G73)) | K73: =IF(A73="","",IF(AND(AND('控制台'!B4<>"",'控制台'!B5<>"",'控制台'!B4='刷新信息'!B6,'控制台'!B5='刷新信息'!B8),A73='控制台'!B4,B73='控制台'!B5,OR(C73="应收",C73="应付"),COUNTIFS('往来余额'!A5:A6000,C73,'往来余额'!B5:B6000,D73)=1,E73<>"",COUNTIFS(A$5:A$504,A73,B$5:B$504,B73,C$5:C$504,C73,D$5:D$504,D73,E$5:E$504,E73)=1,ISNUMBER(F73),I73>=0,ISNUMBER(H73),H73>=0),"纳入","待核实"))
I74: =IF(OR(A74<> '控制台'!B4,B74<> '控制台'!B5,F74=""),"",DATE(VALUE(LEFT('控制台'!B5,4)),VALUE(RIGHT('控制台'!B5,2))+1,1)-1-F74) | J74: =IF(OR(A74<> '控制台'!B4,B74<> '控制台'!B5,G74=""),"",MAX(0,DATE(VALUE(LEFT('控制台'!B5,4)),VALUE(RIGHT('控制台'!B5,2))+1,1)-1-G74)) | K74: =IF(A74="","",IF(AND(AND('控制台'!B4<>"",'控制台'!B5<>"",'控制台'!B4='刷新信息'!B6,'控制台'!B5='刷新信息'!B8),A74='控制台'!B4,B74='控制台'!B5,OR(C74="应收",C74="应付"),COUNTIFS('往来余额'!A5:A6000,C74,'往来余额'!B5:B6000,D74)=1,E74<>"",COUNTIFS(A$5:A$504,A74,B$5:B$504,B74,C$5:C$504,C74,D$5:D$504,D74,E$5:E$504,E74)=1,ISNUMBER(F74),I74>=0,ISNUMBER(H74),H74>=0),"纳入","待核实"))
I75: =IF(OR(A75<> '控制台'!B4,B75<> '控制台'!B5,F75=""),"",DATE(VALUE(LEFT('控制台'!B5,4)),VALUE(RIGHT('控制台'!B5,2))+1,1)-1-F75) | J75: =IF(OR(A75<> '控制台'!B4,B75<> '控制台'!B5,G75=""),"",MAX(0,DATE(VALUE(LEFT('控制台'!B5,4)),VALUE(RIGHT('控制台'!B5,2))+1,1)-1-G75)) | K75: =IF(A75="","",IF(AND(AND('控制台'!B4<>"",'控制台'!B5<>"",'控制台'!B4='刷新信息'!B6,'控制台'!B5='刷新信息'!B8),A75='控制台'!B4,B75='控制台'!B5,OR(C75="应收",C75="应付"),COUNTIFS('往来余额'!A5:A6000,C75,'往来余额'!B5:B6000,D75)=1,E75<>"",COUNTIFS(A$5:A$504,A75,B$5:B$504,B75,C$5:C$504,C75,D$5:D$504,D75,E$5:E$504,E75)=1,ISNUMBER(F75),I75>=0,ISNUMBER(H75),H75>=0),"纳入","待核实"))
I76: =IF(OR(A76<> '控制台'!B4,B76<> '控制台'!B5,F76=""),"",DATE(VALUE(LEFT('控制台'!B5,4)),VALUE(RIGHT('控制台'!B5,2))+1,1)-1-F76) | J76: =IF(OR(A76<> '控制台'!B4,B76<> '控制台'!B5,G76=""),"",MAX(0,DATE(VALUE(LEFT('控制台'!B5,4)),VALUE(RIGHT('控制台'!B5,2))+1,1)-1-G76)) | K76: =IF(A76="","",IF(AND(AND('控制台'!B4<>"",'控制台'!B5<>"",'控制台'!B4='刷新信息'!B6,'控制台'!B5='刷新信息'!B8),A76='控制台'!B4,B76='控制台'!B5,OR(C76="应收",C76="应付"),COUNTIFS('往来余额'!A5:A6000,C76,'往来余额'!B5:B6000,D76)=1,E76<>"",COUNTIFS(A$5:A$504,A76,B$5:B$504,B76,C$5:C$504,C76,D$5:D$504,D76,E$5:E$504,E76)=1,ISNUMBER(F76),I76>=0,ISNUMBER(H76),H76>=0),"纳入","待核实"))
I77: =IF(OR(A77<> '控制台'!B4,B77<> '控制台'!B5,F77=""),"",DATE(VALUE(LEFT('控制台'!B5,4)),VALUE(RIGHT('控制台'!B5,2))+1,1)-1-F77) | J77: =IF(OR(A77<> '控制台'!B4,B77<> '控制台'!B5,G77=""),"",MAX(0,DATE(VALUE(LEFT('控制台'!B5,4)),VALUE(RIGHT('控制台'!B5,2))+1,1)-1-G77)) | K77: =IF(A77="","",IF(AND(AND('控制台'!B4<>"",'控制台'!B5<>"",'控制台'!B4='刷新信息'!B6,'控制台'!B5='刷新信息'!B8),A77='控制台'!B4,B77='控制台'!B5,OR(C77="应收",C77="应付"),COUNTIFS('往来余额'!A5:A6000,C77,'往来余额'!B5:B6000,D77)=1,E77<>"",COUNTIFS(A$5:A$504,A77,B$5:B$504,B77,C$5:C$504,C77,D$5:D$504,D77,E$5:E$504,E77)=1,ISNUMBER(F77),I77>=0,ISNUMBER(H77),H77>=0),"纳入","待核实"))
I78: =IF(OR(A78<> '控制台'!B4,B78<> '控制台'!B5,F78=""),"",DATE(VALUE(LEFT('控制台'!B5,4)),VALUE(RIGHT('控制台'!B5,2))+1,1)-1-F78) | J78: =IF(OR(A78<> '控制台'!B4,B78<> '控制台'!B5,G78=""),"",MAX(0,DATE(VALUE(LEFT('控制台'!B5,4)),VALUE(RIGHT('控制台'!B5,2))+1,1)-1-G78)) | K78: =IF(A78="","",IF(AND(AND('控制台'!B4<>"",'控制台'!B5<>"",'控制台'!B4='刷新信息'!B6,'控制台'!B5='刷新信息'!B8),A78='控制台'!B4,B78='控制台'!B5,OR(C78="应收",C78="应付"),COUNTIFS('往来余额'!A5:A6000,C78,'往来余额'!B5:B6000,D78)=1,E78<>"",COUNTIFS(A$5:A$504,A78,B$5:B$504,B78,C$5:C$504,C78,D$5:D$504,D78,E$5:E$504,E78)=1,ISNUMBER(F78),I78>=0,ISNUMBER(H78),H78>=0),"纳入","待核实"))
I79: =IF(OR(A79<> '控制台'!B4,B79<> '控制台'!B5,F79=""),"",DATE(VALUE(LEFT('控制台'!B5,4)),VALUE(RIGHT('控制台'!B5,2))+1,1)-1-F79) | J79: =IF(OR(A79<> '控制台'!B4,B79<> '控制台'!B5,G79=""),"",MAX(0,DATE(VALUE(LEFT('控制台'!B5,4)),VALUE(RIGHT('控制台'!B5,2))+1,1)-1-G79)) | K79: =IF(A79="","",IF(AND(AND('控制台'!B4<>"",'控制台'!B5<>"",'控制台'!B4='刷新信息'!B6,'控制台'!B5='刷新信息'!B8),A79='控制台'!B4,B79='控制台'!B5,OR(C79="应收",C79="应付"),COUNTIFS('往来余额'!A5:A6000,C79,'往来余额'!B5:B6000,D79)=1,E79<>"",COUNTIFS(A$5:A$504,A79,B$5:B$504,B79,C$5:C$504,C79,D$5:D$504,D79,E$5:E$504,E79)=1,ISNUMBER(F79),I79>=0,ISNUMBER(H79),H79>=0),"纳入","待核实"))
I80: =IF(OR(A80<> '控制台'!B4,B80<> '控制台'!B5,F80=""),"",DATE(VALUE(LEFT('控制台'!B5,4)),VALUE(RIGHT('控制台'!B5,2))+1,1)-1-F80) | J80: =IF(OR(A80<> '控制台'!B4,B80<> '控制台'!B5,G80=""),"",MAX(0,DATE(VALUE(LEFT('控制台'!B5,4)),VALUE(RIGHT('控制台'!B5,2))+1,1)-1-G80)) | K80: =IF(A80="","",IF(AND(AND('控制台'!B4<>"",'控制台'!B5<>"",'控制台'!B4='刷新信息'!B6,'控制台'!B5='刷新信息'!B8),A80='控制台'!B4,B80='控制台'!B5,OR(C80="应收",C80="应付"),COUNTIFS('往来余额'!A5:A6000,C80,'往来余额'!B5:B6000,D80)=1,E80<>"",COUNTIFS(A$5:A$504,A80,B$5:B$504,B80,C$5:C$504,C80,D$5:D$504,D80,E$5:E$504,E80)=1,ISNUMBER(F80),I80>=0,ISNUMBER(H80),H80>=0),"纳入","待核实"))
I81: =IF(OR(A81<> '控制台'!B4,B81<> '控制台'!B5,F81=""),"",DATE(VALUE(LEFT('控制台'!B5,4)),VALUE(RIGHT('控制台'!B5,2))+1,1)-1-F81) | J81: =IF(OR(A81<> '控制台'!B4,B81<> '控制台'!B5,G81=""),"",MAX(0,DATE(VALUE(LEFT('控制台'!B5,4)),VALUE(RIGHT('控制台'!B5,2))+1,1)-1-G81)) | K81: =IF(A81="","",IF(AND(AND('控制台'!B4<>"",'控制台'!B5<>"",'控制台'!B4='刷新信息'!B6,'控制台'!B5='刷新信息'!B8),A81='控制台'!B4,B81='控制台'!B5,OR(C81="应收",C81="应付"),COUNTIFS('往来余额'!A5:A6000,C81,'往来余额'!B5:B6000,D81)=1,E81<>"",COUNTIFS(A$5:A$504,A81,B$5:B$504,B81,C$5:C$504,C81,D$5:D$504,D81,E$5:E$504,E81)=1,ISNUMBER(F81),I81>=0,ISNUMBER(H81),H81>=0),"纳入","待核实"))
I82: =IF(OR(A82<> '控制台'!B4,B82<> '控制台'!B5,F82=""),"",DATE(VALUE(LEFT('控制台'!B5,4)),VALUE(RIGHT('控制台'!B5,2))+1,1)-1-F82) | J82: =IF(OR(A82<> '控制台'!B4,B82<> '控制台'!B5,G82=""),"",MAX(0,DATE(VALUE(LEFT('控制台'!B5,4)),VALUE(RIGHT('控制台'!B5,2))+1,1)-1-G82)) | K82: =IF(A82="","",IF(AND(AND('控制台'!B4<>"",'控制台'!B5<>"",'控制台'!B4='刷新信息'!B6,'控制台'!B5='刷新信息'!B8),A82='控制台'!B4,B82='控制台'!B5,OR(C82="应收",C82="应付"),COUNTIFS('往来余额'!A5:A6000,C82,'往来余额'!B5:B6000,D82)=1,E82<>"",COUNTIFS(A$5:A$504,A82,B$5:B$504,B82,C$5:C$504,C82,D$5:D$504,D82,E$5:E$504,E82)=1,ISNUMBER(F82),I82>=0,ISNUMBER(H82),H82>=0),"纳入","待核实"))
I83: =IF(OR(A83<> '控制台'!B4,B83<> '控制台'!B5,F83=""),"",DATE(VALUE(LEFT('控制台'!B5,4)),VALUE(RIGHT('控制台'!B5,2))+1,1)-1-F83) | J83: =IF(OR(A83<> '控制台'!B4,B83<> '控制台'!B5,G83=""),"",MAX(0,DATE(VALUE(LEFT('控制台'!B5,4)),VALUE(RIGHT('控制台'!B5,2))+1,1)-1-G83)) | K83: =IF(A83="","",IF(AND(AND('控制台'!B4<>"",'控制台'!B5<>"",'控制台'!B4='刷新信息'!B6,'控制台'!B5='刷新信息'!B8),A83='控制台'!B4,B83='控制台'!B5,OR(C83="应收",C83="应付"),COUNTIFS('往来余额'!A5:A6000,C83,'往来余额'!B5:B6000,D83)=1,E83<>"",COUNTIFS(A$5:A$504,A83,B$5:B$504,B83,C$5:C$504,C83,D$5:D$504,D83,E$5:E$504,E83)=1,ISNUMBER(F83),I83>=0,ISNUMBER(H83),H83>=0),"纳入","待核实"))
I84: =IF(OR(A84<> '控制台'!B4,B84<> '控制台'!B5,F84=""),"",DATE(VALUE(LEFT('控制台'!B5,4)),VALUE(RIGHT('控制台'!B5,2))+1,1)-1-F84) | J84: =IF(OR(A84<> '控制台'!B4,B84<> '控制台'!B5,G84=""),"",MAX(0,DATE(VALUE(LEFT('控制台'!B5,4)),VALUE(RIGHT('控制台'!B5,2))+1,1)-1-G84)) | K84: =IF(A84="","",IF(AND(AND('控制台'!B4<>"",'控制台'!B5<>"",'控制台'!B4='刷新信息'!B6,'控制台'!B5='刷新信息'!B8),A84='控制台'!B4,B84='控制台'!B5,OR(C84="应收",C84="应付"),COUNTIFS('往来余额'!A5:A6000,C84,'往来余额'!B5:B6000,D84)=1,E84<>"",COUNTIFS(A$5:A$504,A84,B$5:B$504,B84,C$5:C$504,C84,D$5:D$504,D84,E$5:E$504,E84)=1,ISNUMBER(F84),I84>=0,ISNUMBER(H84),H84>=0),"纳入","待核实"))
I85: =IF(OR(A85<> '控制台'!B4,B85<> '控制台'!B5,F85=""),"",DATE(VALUE(LEFT('控制台'!B5,4)),VALUE(RIGHT('控制台'!B5,2))+1,1)-1-F85) | J85: =IF(OR(A85<> '控制台'!B4,B85<> '控制台'!B5,G85=""),"",MAX(0,DATE(VALUE(LEFT('控制台'!B5,4)),VALUE(RIGHT('控制台'!B5,2))+1,1)-1-G85)) | K85: =IF(A85="","",IF(AND(AND('控制台'!B4<>"",'控制台'!B5<>"",'控制台'!B4='刷新信息'!B6,'控制台'!B5='刷新信息'!B8),A85='控制台'!B4,B85='控制台'!B5,OR(C85="应收",C85="应付"),COUNTIFS('往来余额'!A5:A6000,C85,'往来余额'!B5:B6000,D85)=1,E85<>"",COUNTIFS(A$5:A$504,A85,B$5:B$504,B85,C$5:C$504,C85,D$5:D$504,D85,E$5:E$504,E85)=1,ISNUMBER(F85),I85>=0,ISNUMBER(H85),H85>=0),"纳入","待核实"))
I86: =IF(OR(A86<> '控制台'!B4,B86<> '控制台'!B5,F86=""),"",DATE(VALUE(LEFT('控制台'!B5,4)),VALUE(RIGHT('控制台'!B5,2))+1,1)-1-F86) | J86: =IF(OR(A86<> '控制台'!B4,B86<> '控制台'!B5,G86=""),"",MAX(0,DATE(VALUE(LEFT('控制台'!B5,4)),VALUE(RIGHT('控制台'!B5,2))+1,1)-1-G86)) | K86: =IF(A86="","",IF(AND(AND('控制台'!B4<>"",'控制台'!B5<>"",'控制台'!B4='刷新信息'!B6,'控制台'!B5='刷新信息'!B8),A86='控制台'!B4,B86='控制台'!B5,OR(C86="应收",C86="应付"),COUNTIFS('往来余额'!A5:A6000,C86,'往来余额'!B5:B6000,D86)=1,E86<>"",COUNTIFS(A$5:A$504,A86,B$5:B$504,B86,C$5:C$504,C86,D$5:D$504,D86,E$5:E$504,E86)=1,ISNUMBER(F86),I86>=0,ISNUMBER(H86),H86>=0),"纳入","待核实"))
I87: =IF(OR(A87<> '控制台'!B4,B87<> '控制台'!B5,F87=""),"",DATE(VALUE(LEFT('控制台'!B5,4)),VALUE(RIGHT('控制台'!B5,2))+1,1)-1-F87) | J87: =IF(OR(A87<> '控制台'!B4,B87<> '控制台'!B5,G87=""),"",MAX(0,DATE(VALUE(LEFT('控制台'!B5,4)),VALUE(RIGHT('控制台'!B5,2))+1,1)-1-G87)) | K87: =IF(A87="","",IF(AND(AND('控制台'!B4<>"",'控制台'!B5<>"",'控制台'!B4='刷新信息'!B6,'控制台'!B5='刷新信息'!B8),A87='控制台'!B4,B87='控制台'!B5,OR(C87="应收",C87="应付"),COUNTIFS('往来余额'!A5:A6000,C87,'往来余额'!B5:B6000,D87)=1,E87<>"",COUNTIFS(A$5:A$504,A87,B$5:B$504,B87,C$5:C$504,C87,D$5:D$504,D87,E$5:E$504,E87)=1,ISNUMBER(F87),I87>=0,ISNUMBER(H87),H87>=0),"纳入","待核实"))
I88: =IF(OR(A88<> '控制台'!B4,B88<> '控制台'!B5,F88=""),"",DATE(VALUE(LEFT('控制台'!B5,4)),VALUE(RIGHT('控制台'!B5,2))+1,1)-1-F88) | J88: =IF(OR(A88<> '控制台'!B4,B88<> '控制台'!B5,G88=""),"",MAX(0,DATE(VALUE(LEFT('控制台'!B5,4)),VALUE(RIGHT('控制台'!B5,2))+1,1)-1-G88)) | K88: =IF(A88="","",IF(AND(AND('控制台'!B4<>"",'控制台'!B5<>"",'控制台'!B4='刷新信息'!B6,'控制台'!B5='刷新信息'!B8),A88='控制台'!B4,B88='控制台'!B5,OR(C88="应收",C88="应付"),COUNTIFS('往来余额'!A5:A6000,C88,'往来余额'!B5:B6000,D88)=1,E88<>"",COUNTIFS(A$5:A$504,A88,B$5:B$504,B88,C$5:C$504,C88,D$5:D$504,D88,E$5:E$504,E88)=1,ISNUMBER(F88),I88>=0,ISNUMBER(H88),H88>=0),"纳入","待核实"))
I89: =IF(OR(A89<> '控制台'!B4,B89<> '控制台'!B5,F89=""),"",DATE(VALUE(LEFT('控制台'!B5,4)),VALUE(RIGHT('控制台'!B5,2))+1,1)-1-F89) | J89: =IF(OR(A89<> '控制台'!B4,B89<> '控制台'!B5,G89=""),"",MAX(0,DATE(VALUE(LEFT('控制台'!B5,4)),VALUE(RIGHT('控制台'!B5,2))+1,1)-1-G89)) | K89: =IF(A89="","",IF(AND(AND('控制台'!B4<>"",'控制台'!B5<>"",'控制台'!B4='刷新信息'!B6,'控制台'!B5='刷新信息'!B8),A89='控制台'!B4,B89='控制台'!B5,OR(C89="应收",C89="应付"),COUNTIFS('往来余额'!A5:A6000,C89,'往来余额'!B5:B6000,D89)=1,E89<>"",COUNTIFS(A$5:A$504,A89,B$5:B$504,B89,C$5:C$504,C89,D$5:D$504,D89,E$5:E$504,E89)=1,ISNUMBER(F89),I89>=0,ISNUMBER(H89),H89>=0),"纳入","待核实"))
I90: =IF(OR(A90<> '控制台'!B4,B90<> '控制台'!B5,F90=""),"",DATE(VALUE(LEFT('控制台'!B5,4)),VALUE(RIGHT('控制台'!B5,2))+1,1)-1-F90) | J90: =IF(OR(A90<> '控制台'!B4,B90<> '控制台'!B5,G90=""),"",MAX(0,DATE(VALUE(LEFT('控制台'!B5,4)),VALUE(RIGHT('控制台'!B5,2))+1,1)-1-G90)) | K90: =IF(A90="","",IF(AND(AND('控制台'!B4<>"",'控制台'!B5<>"",'控制台'!B4='刷新信息'!B6,'控制台'!B5='刷新信息'!B8),A90='控制台'!B4,B90='控制台'!B5,OR(C90="应收",C90="应付"),COUNTIFS('往来余额'!A5:A6000,C90,'往来余额'!B5:B6000,D90)=1,E90<>"",COUNTIFS(A$5:A$504,A90,B$5:B$504,B90,C$5:C$504,C90,D$5:D$504,D90,E$5:E$504,E90)=1,ISNUMBER(F90),I90>=0,ISNUMBER(H90),H90>=0),"纳入","待核实"))
I91: =IF(OR(A91<> '控制台'!B4,B91<> '控制台'!B5,F91=""),"",DATE(VALUE(LEFT('控制台'!B5,4)),VALUE(RIGHT('控制台'!B5,2))+1,1)-1-F91) | J91: =IF(OR(A91<> '控制台'!B4,B91<> '控制台'!B5,G91=""),"",MAX(0,DATE(VALUE(LEFT('控制台'!B5,4)),VALUE(RIGHT('控制台'!B5,2))+1,1)-1-G91)) | K91: =IF(A91="","",IF(AND(AND('控制台'!B4<>"",'控制台'!B5<>"",'控制台'!B4='刷新信息'!B6,'控制台'!B5='刷新信息'!B8),A91='控制台'!B4,B91='控制台'!B5,OR(C91="应收",C91="应付"),COUNTIFS('往来余额'!A5:A6000,C91,'往来余额'!B5:B6000,D91)=1,E91<>"",COUNTIFS(A$5:A$504,A91,B$5:B$504,B91,C$5:C$504,C91,D$5:D$504,D91,E$5:E$504,E91)=1,ISNUMBER(F91),I91>=0,ISNUMBER(H91),H91>=0),"纳入","待核实"))
I92: =IF(OR(A92<> '控制台'!B4,B92<> '控制台'!B5,F92=""),"",DATE(VALUE(LEFT('控制台'!B5,4)),VALUE(RIGHT('控制台'!B5,2))+1,1)-1-F92) | J92: =IF(OR(A92<> '控制台'!B4,B92<> '控制台'!B5,G92=""),"",MAX(0,DATE(VALUE(LEFT('控制台'!B5,4)),VALUE(RIGHT('控制台'!B5,2))+1,1)-1-G92)) | K92: =IF(A92="","",IF(AND(AND('控制台'!B4<>"",'控制台'!B5<>"",'控制台'!B4='刷新信息'!B6,'控制台'!B5='刷新信息'!B8),A92='控制台'!B4,B92='控制台'!B5,OR(C92="应收",C92="应付"),COUNTIFS('往来余额'!A5:A6000,C92,'往来余额'!B5:B6000,D92)=1,E92<>"",COUNTIFS(A$5:A$504,A92,B$5:B$504,B92,C$5:C$504,C92,D$5:D$504,D92,E$5:E$504,E92)=1,ISNUMBER(F92),I92>=0,ISNUMBER(H92),H92>=0),"纳入","待核实"))
I93: =IF(OR(A93<> '控制台'!B4,B93<> '控制台'!B5,F93=""),"",DATE(VALUE(LEFT('控制台'!B5,4)),VALUE(RIGHT('控制台'!B5,2))+1,1)-1-F93) | J93: =IF(OR(A93<> '控制台'!B4,B93<> '控制台'!B5,G93=""),"",MAX(0,DATE(VALUE(LEFT('控制台'!B5,4)),VALUE(RIGHT('控制台'!B5,2))+1,1)-1-G93)) | K93: =IF(A93="","",IF(AND(AND('控制台'!B4<>"",'控制台'!B5<>"",'控制台'!B4='刷新信息'!B6,'控制台'!B5='刷新信息'!B8),A93='控制台'!B4,B93='控制台'!B5,OR(C93="应收",C93="应付"),COUNTIFS('往来余额'!A5:A6000,C93,'往来余额'!B5:B6000,D93)=1,E93<>"",COUNTIFS(A$5:A$504,A93,B$5:B$504,B93,C$5:C$504,C93,D$5:D$504,D93,E$5:E$504,E93)=1,ISNUMBER(F93),I93>=0,ISNUMBER(H93),H93>=0),"纳入","待核实"))
I94: =IF(OR(A94<> '控制台'!B4,B94<> '控制台'!B5,F94=""),"",DATE(VALUE(LEFT('控制台'!B5,4)),VALUE(RIGHT('控制台'!B5,2))+1,1)-1-F94) | J94: =IF(OR(A94<> '控制台'!B4,B94<> '控制台'!B5,G94=""),"",MAX(0,DATE(VALUE(LEFT('控制台'!B5,4)),VALUE(RIGHT('控制台'!B5,2))+1,1)-1-G94)) | K94: =IF(A94="","",IF(AND(AND('控制台'!B4<>"",'控制台'!B5<>"",'控制台'!B4='刷新信息'!B6,'控制台'!B5='刷新信息'!B8),A94='控制台'!B4,B94='控制台'!B5,OR(C94="应收",C94="应付"),COUNTIFS('往来余额'!A5:A6000,C94,'往来余额'!B5:B6000,D94)=1,E94<>"",COUNTIFS(A$5:A$504,A94,B$5:B$504,B94,C$5:C$504,C94,D$5:D$504,D94,E$5:E$504,E94)=1,ISNUMBER(F94),I94>=0,ISNUMBER(H94),H94>=0),"纳入","待核实"))
I95: =IF(OR(A95<> '控制台'!B4,B95<> '控制台'!B5,F95=""),"",DATE(VALUE(LEFT('控制台'!B5,4)),VALUE(RIGHT('控制台'!B5,2))+1,1)-1-F95) | J95: =IF(OR(A95<> '控制台'!B4,B95<> '控制台'!B5,G95=""),"",MAX(0,DATE(VALUE(LEFT('控制台'!B5,4)),VALUE(RIGHT('控制台'!B5,2))+1,1)-1-G95)) | K95: =IF(A95="","",IF(AND(AND('控制台'!B4<>"",'控制台'!B5<>"",'控制台'!B4='刷新信息'!B6,'控制台'!B5='刷新信息'!B8),A95='控制台'!B4,B95='控制台'!B5,OR(C95="应收",C95="应付"),COUNTIFS('往来余额'!A5:A6000,C95,'往来余额'!B5:B6000,D95)=1,E95<>"",COUNTIFS(A$5:A$504,A95,B$5:B$504,B95,C$5:C$504,C95,D$5:D$504,D95,E$5:E$504,E95)=1,ISNUMBER(F95),I95>=0,ISNUMBER(H95),H95>=0),"纳入","待核实"))
I96: =IF(OR(A96<> '控制台'!B4,B96<> '控制台'!B5,F96=""),"",DATE(VALUE(LEFT('控制台'!B5,4)),VALUE(RIGHT('控制台'!B5,2))+1,1)-1-F96) | J96: =IF(OR(A96<> '控制台'!B4,B96<> '控制台'!B5,G96=""),"",MAX(0,DATE(VALUE(LEFT('控制台'!B5,4)),VALUE(RIGHT('控制台'!B5,2))+1,1)-1-G96)) | K96: =IF(A96="","",IF(AND(AND('控制台'!B4<>"",'控制台'!B5<>"",'控制台'!B4='刷新信息'!B6,'控制台'!B5='刷新信息'!B8),A96='控制台'!B4,B96='控制台'!B5,OR(C96="应收",C96="应付"),COUNTIFS('往来余额'!A5:A6000,C96,'往来余额'!B5:B6000,D96)=1,E96<>"",COUNTIFS(A$5:A$504,A96,B$5:B$504,B96,C$5:C$504,C96,D$5:D$504,D96,E$5:E$504,E96)=1,ISNUMBER(F96),I96>=0,ISNUMBER(H96),H96>=0),"纳入","待核实"))
I97: =IF(OR(A97<> '控制台'!B4,B97<> '控制台'!B5,F97=""),"",DATE(VALUE(LEFT('控制台'!B5,4)),VALUE(RIGHT('控制台'!B5,2))+1,1)-1-F97) | J97: =IF(OR(A97<> '控制台'!B4,B97<> '控制台'!B5,G97=""),"",MAX(0,DATE(VALUE(LEFT('控制台'!B5,4)),VALUE(RIGHT('控制台'!B5,2))+1,1)-1-G97)) | K97: =IF(A97="","",IF(AND(AND('控制台'!B4<>"",'控制台'!B5<>"",'控制台'!B4='刷新信息'!B6,'控制台'!B5='刷新信息'!B8),A97='控制台'!B4,B97='控制台'!B5,OR(C97="应收",C97="应付"),COUNTIFS('往来余额'!A5:A6000,C97,'往来余额'!B5:B6000,D97)=1,E97<>"",COUNTIFS(A$5:A$504,A97,B$5:B$504,B97,C$5:C$504,C97,D$5:D$504,D97,E$5:E$504,E97)=1,ISNUMBER(F97),I97>=0,ISNUMBER(H97),H97>=0),"纳入","待核实"))
I98: =IF(OR(A98<> '控制台'!B4,B98<> '控制台'!B5,F98=""),"",DATE(VALUE(LEFT('控制台'!B5,4)),VALUE(RIGHT('控制台'!B5,2))+1,1)-1-F98) | J98: =IF(OR(A98<> '控制台'!B4,B98<> '控制台'!B5,G98=""),"",MAX(0,DATE(VALUE(LEFT('控制台'!B5,4)),VALUE(RIGHT('控制台'!B5,2))+1,1)-1-G98)) | K98: =IF(A98="","",IF(AND(AND('控制台'!B4<>"",'控制台'!B5<>"",'控制台'!B4='刷新信息'!B6,'控制台'!B5='刷新信息'!B8),A98='控制台'!B4,B98='控制台'!B5,OR(C98="应收",C98="应付"),COUNTIFS('往来余额'!A5:A6000,C98,'往来余额'!B5:B6000,D98)=1,E98<>"",COUNTIFS(A$5:A$504,A98,B$5:B$504,B98,C$5:C$504,C98,D$5:D$504,D98,E$5:E$504,E98)=1,ISNUMBER(F98),I98>=0,ISNUMBER(H98),H98>=0),"纳入","待核实"))
I99: =IF(OR(A99<> '控制台'!B4,B99<> '控制台'!B5,F99=""),"",DATE(VALUE(LEFT('控制台'!B5,4)),VALUE(RIGHT('控制台'!B5,2))+1,1)-1-F99) | J99: =IF(OR(A99<> '控制台'!B4,B99<> '控制台'!B5,G99=""),"",MAX(0,DATE(VALUE(LEFT('控制台'!B5,4)),VALUE(RIGHT('控制台'!B5,2))+1,1)-1-G99)) | K99: =IF(A99="","",IF(AND(AND('控制台'!B4<>"",'控制台'!B5<>"",'控制台'!B4='刷新信息'!B6,'控制台'!B5='刷新信息'!B8),A99='控制台'!B4,B99='控制台'!B5,OR(C99="应收",C99="应付"),COUNTIFS('往来余额'!A5:A6000,C99,'往来余额'!B5:B6000,D99)=1,E99<>"",COUNTIFS(A$5:A$504,A99,B$5:B$504,B99,C$5:C$504,C99,D$5:D$504,D99,E$5:E$504,E99)=1,ISNUMBER(F99),I99>=0,ISNUMBER(H99),H99>=0),"纳入","待核实"))
I100: =IF(OR(A100<> '控制台'!B4,B100<> '控制台'!B5,F100=""),"",DATE(VALUE(LEFT('控制台'!B5,4)),VALUE(RIGHT('控制台'!B5,2))+1,1)-1-F100) | J100: =IF(OR(A100<> '控制台'!B4,B100<> '控制台'!B5,G100=""),"",MAX(0,DATE(VALUE(LEFT('控制台'!B5,4)),VALUE(RIGHT('控制台'!B5,2))+1,1)-1-G100)) | K100: =IF(A100="","",IF(AND(AND('控制台'!B4<>"",'控制台'!B5<>"",'控制台'!B4='刷新信息'!B6,'控制台'!B5='刷新信息'!B8),A100='控制台'!B4,B100='控制台'!B5,OR(C100="应收",C100="应付"),COUNTIFS('往来余额'!A5:A6000,C100,'往来余额'!B5:B6000,D100)=1,E100<>"",COUNTIFS(A$5:A$504,A100,B$5:B$504,B100,C$5:C$504,C100,D$5:D$504,D100,E$5:E$504,E100)=1,ISNUMBER(F100),I100>=0,ISNUMBER(H100),H100>=0),"纳入","待核实"))
I101: =IF(OR(A101<> '控制台'!B4,B101<> '控制台'!B5,F101=""),"",DATE(VALUE(LEFT('控制台'!B5,4)),VALUE(RIGHT('控制台'!B5,2))+1,1)-1-F101) | J101: =IF(OR(A101<> '控制台'!B4,B101<> '控制台'!B5,G101=""),"",MAX(0,DATE(VALUE(LEFT('控制台'!B5,4)),VALUE(RIGHT('控制台'!B5,2))+1,1)-1-G101)) | K101: =IF(A101="","",IF(AND(AND('控制台'!B4<>"",'控制台'!B5<>"",'控制台'!B4='刷新信息'!B6,'控制台'!B5='刷新信息'!B8),A101='控制台'!B4,B101='控制台'!B5,OR(C101="应收",C101="应付"),COUNTIFS('往来余额'!A5:A6000,C101,'往来余额'!B5:B6000,D101)=1,E101<>"",COUNTIFS(A$5:A$504,A101,B$5:B$504,B101,C$5:C$504,C101,D$5:D$504,D101,E$5:E$504,E101)=1,ISNUMBER(F101),I101>=0,ISNUMBER(H101),H101>=0),"纳入","待核实"))
...

Sheet 账龄统计
A1: 账龄统计
A2: 按发生日计算账龄；逾期按到期日计算。未分配金额不推断账龄。
A4: 类型 | B4: 往来净余额 | C4: 已分配单据 | D4: 未分配净额 | E4: 0–30天 | F4: 31–60天 | G4: 61–90天 | H4: 91–180天 | I4: 181–365天 | J4: 365天以上 | K4: 逾期金额
A5: 应收 | B5: =IF(AND('控制台'!B4<>"",'控制台'!B5<>"",'控制台'!B4='刷新信息'!B6,'控制台'!B5='刷新信息'!B8),'经营统计'!B11,"") | C5: =IF(AND('控制台'!B4<>"",'控制台'!B5<>"",'控制台'!B4='刷新信息'!B6,'控制台'!B5='刷新信息'!B8),SUMIFS('账龄输入'!H5:H504,'账龄输入'!C5:C504,A5,'账龄输入'!K5:K504,"纳入"),"") | D5: =IF(AND('控制台'!B4<>"",'控制台'!B5<>"",'控制台'!B4='刷新信息'!B6,'控制台'!B5='刷新信息'!B8),B5-C5,"") | E5: =IF(AND('控制台'!B4<>"",'控制台'!B5<>"",'控制台'!B4='刷新信息'!B6,'控制台'!B5='刷新信息'!B8),SUMIFS('账龄输入'!H5:H504,'账龄输入'!C5:C504,A5,'账龄输入'!K5:K504,"纳入",'账龄输入'!I5:I504,">=0",'账龄输入'!I5:I504,"<=30"),"") | F5: =IF(AND('控制台'!B4<>"",'控制台'!B5<>"",'控制台'!B4='刷新信息'!B6,'控制台'!B5='刷新信息'!B8),SUMIFS('账龄输入'!H5:H504,'账龄输入'!C5:C504,A5,'账龄输入'!K5:K504,"纳入",'账龄输入'!I5:I504,">=31",'账龄输入'!I5:I504,"<=60"),"") | G5: =IF(AND('控制台'!B4<>"",'控制台'!B5<>"",'控制台'!B4='刷新信息'!B6,'控制台'!B5='刷新信息'!B8),SUMIFS('账龄输入'!H5:H504,'账龄输入'!C5:C504,A5,'账龄输入'!K5:K504,"纳入",'账龄输入'!I5:I504,">=61",'账龄输入'!I5:I504,"<=90"),"") | H5: =IF(AND('控制台'!B4<>"",'控制台'!B5<>"",'控制台'!B4='刷新信息'!B6,'控制台'!B5='刷新信息'!B8),SUMIFS('账龄输入'!H5:H504,'账龄输入'!C5:C504,A5,'账龄输入'!K5:K504,"纳入",'账龄输入'!I5:I504,">=91",'账龄输入'!I5:I504,"<=180"),"") | I5: =IF(AND('控制台'!B4<>"",'控制台'!B5<>"",'控制台'!B4='刷新信息'!B6,'控制台'!B5='刷新信息'!B8),SUMIFS('账龄输入'!H5:H504,'账龄输入'!C5:C504,A5,'账龄输入'!K5:K504,"纳入",'账龄输入'!I5:I504,">=181",'账龄输入'!I5:I504,"<=365"),"") | J5: =IF(AND('控制台'!B4<>"",'控制台'!B5<>"",'控制台'!B4='刷新信息'!B6,'控制台'!B5='刷新信息'!B8),SUMIFS('账龄输入'!H5:H504,'账龄输入'!C5:C504,A5,'账龄输入'!K5:K504,"纳入",'账龄输入'!I5:I504,">=366",'账龄输入'!I5:I504,"<=999999"),"") | K5: =IF(AND('控制台'!B4<>"",'控制台'!B5<>"",'控制台'!B4='刷新信息'!B6,'控制台'!B5='刷新信息'!B8),SUMIFS('账龄输入'!H5:H504,'账龄输入'!C5:C504,A5,'账龄输入'!K5:K504,"纳入",'账龄输入'!J5:J504,">0"),"")
A6: 应付 | B6: =IF(AND('控制台'!B4<>"",'控制台'!B5<>"",'控制台'!B4='刷新信息'!B6,'控制台'!B5='刷新信息'!B8),'经营统计'!B12,"") | C6: =IF(AND('控制台'!B4<>"",'控制台'!B5<>"",'控制台'!B4='刷新信息'!B6,'控制台'!B5='刷新信息'!B8),SUMIFS('账龄输入'!H5:H504,'账龄输入'!C5:C504,A6,'账龄输入'!K5:K504,"纳入"),"") | D6: =IF(AND('控制台'!B4<>"",'控制台'!B5<>"",'控制台'!B4='刷新信息'!B6,'控制台'!B5='刷新信息'!B8),B6-C6,"") | E6: =IF(AND('控制台'!B4<>"",'控制台'!B5<>"",'控制台'!B4='刷新信息'!B6,'控制台'!B5='刷新信息'!B8),SUMIFS('账龄输入'!H5:H504,'账龄输入'!C5:C504,A6,'账龄输入'!K5:K504,"纳入",'账龄输入'!I5:I504,">=0",'账龄输入'!I5:I504,"<=30"),"") | F6: =IF(AND('控制台'!B4<>"",'控制台'!B5<>"",'控制台'!B4='刷新信息'!B6,'控制台'!B5='刷新信息'!B8),SUMIFS('账龄输入'!H5:H504,'账龄输入'!C5:C504,A6,'账龄输入'!K5:K504,"纳入",'账龄输入'!I5:I504,">=31",'账龄输入'!I5:I504,"<=60"),"") | G6: =IF(AND('控制台'!B4<>"",'控制台'!B5<>"",'控制台'!B4='刷新信息'!B6,'控制台'!B5='刷新信息'!B8),SUMIFS('账龄输入'!H5:H504,'账龄输入'!C5:C504,A6,'账龄输入'!K5:K504,"纳入",'账龄输入'!I5:I504,">=61",'账龄输入'!I5:I504,"<=90"),"") | H6: =IF(AND('控制台'!B4<>"",'控制台'!B5<>"",'控制台'!B4='刷新信息'!B6,'控制台'!B5='刷新信息'!B8),SUMIFS('账龄输入'!H5:H504,'账龄输入'!C5:C504,A6,'账龄输入'!K5:K504,"纳入",'账龄输入'!I5:I504,">=91",'账龄输入'!I5:I504,"<=180"),"") | I6: =IF(AND('控制台'!B4<>"",'控制台'!B5<>"",'控制台'!B4='刷新信息'!B6,'控制台'!B5='刷新信息'!B8),SUMIFS('账龄输入'!H5:H504,'账龄输入'!C5:C504,A6,'账龄输入'!K5:K504,"纳入",'账龄输入'!I5:I504,">=181",'账龄输入'!I5:I504,"<=365"),"") | J6: =IF(AND('控制台'!B4<>"",'控制台'!B5<>"",'控制台'!B4='刷新信息'!B6,'控制台'!B5='刷新信息'!B8),SUMIFS('账龄输入'!H5:H504,'账龄输入'!C5:C504,A6,'账龄输入'!K5:K504,"纳入",'账龄输入'!I5:I504,">=366",'账龄输入'!I5:I504,"<=999999"),"") | K6: =IF(AND('控制台'!B4<>"",'控制台'!B5<>"",'控制台'!B4='刷新信息'!B6,'控制台'!B5='刷新信息'!B8),SUMIFS('账龄输入'!H5:H504,'账龄输入'!C5:C504,A6,'账龄输入'!K5:K504,"纳入",'账龄输入'!J5:J504,">0"),"")
A9: 未分配净额包括未录入单据及预收预付抵减；不等于已核销差异，也不等于逾期金额。

Sheet 刷新信息
A1: 刷新信息
A2: 尚未读取数据；请先配置刷新连接
A4: 字段 | B4: 值
A5: schema | B5: 1
A6: company
A7: company_name
A8: month
A9: refreshed_at_utc

Sheet 公司列表
A1: 可选公司
A2: 尚未读取数据；请先配置刷新连接
A4: 公司编号 | B4: 公司名称

Sheet 利润表
A1: 利润表
A2: 尚未读取数据；请先配置刷新连接
A4: 项目编码 | B4: 项目 | C4: 本月金额 | D4: 本年累计 | E4: 上年累计 | F4: 统计分类

Sheet 资产负债表
A1: 资产负债表
A2: 尚未读取数据；请先配置刷新连接
A4: 资产 | B4: 期末余额 | C4: 年初余额 | D4: 负债与权益 | E4: 期末余额 | F4: 年初余额

Sheet 现金流量表
A1: 现金流量表
A2: 尚未读取数据；请先配置刷新连接
A4: 区块 | B4: 项目编码 | C4: 项目 | D4: balance | E4: curBalance | F4: preBalance

Sheet 科目余额
A1: 科目余额
A2: 尚未读取数据；请先配置刷新连接
A4: 科目编码 | B4: 科目 | C4: 期初借方 | D4: 期初贷方 | E4: 本期借方 | F4: 本期贷方 | G4: 期末借方 | H4: 期末贷方 | I4: 末级

Sheet 凭证明细
A1: 凭证明细
A2: 尚未读取数据；请先配置刷新连接
A4: 凭证ID | B4: 分录序号 | C4: 日期 | D4: 凭证号 | E4: 科目编码 | F4: 科目名称 | G4: 辅助项目 | H4: 摘要 | I4: 借方 | J4: 贷方 | K4: 币种 | L4: 原币金额 | M4: 收支类型

Sheet 出纳账
A1: 出纳账（总账口径）
A2: 尚未读取数据；请先配置刷新连接
A4: 凭证ID | B4: 分录序号 | C4: 日期 | D4: 凭证号 | E4: 科目编码 | F4: 科目名称 | G4: 辅助项目 | H4: 摘要 | I4: 借方 | J4: 贷方 | K4: 币种 | L4: 原币金额 | M4: 收支类型

Sheet 往来余额
A1: 往来余额
A2: 尚未读取数据；请先配置刷新连接
A4: 类型 | B4: 核算项目ID组合 | C4: 编码 | D4: 名称 | E4: 期初借方 | F4: 期初贷方 | G4: 本期借方 | H4: 本期贷方 | I4: 期末借方 | J4: 期末贷方

Sheet 月度趋势
A1: 利润月度明细
A2: 尚未读取数据；请先配置刷新连接
A4: 月份 | B4: 项目编码 | C4: 项目 | D4: 本月金额 | E4: 统计分类

Sheet 使用说明
A1: 使用说明
A2: 一次性安装按钮后，日常只需选择公司、月份并刷新。
A4: 事项 | B4: 说明
A5: 连接 | B5: Windows 通过 SSH 转发连接 Linux 的只读服务；账无忧会话只保存在后台。
A6: 首次安装 | B6: 运行 scripts/finance/install-excel.ps1，将此 .xlsx 转为 .xlsm 并加入刷新按钮。
A7: 输入保护 | B7: 刷新只替换原始数据表；预算输入、账龄输入及其公式不会被覆盖。
A8: 容量 | B8: 每张接口表最多 6000 行；预算输入 200 行、账龄输入 500 行。超限需要扩展公式。
A9: 账龄 | B9: 当前未接入单据核销与到期日接口；人工补充未核销单据后计算，不伪造自动账龄。
A10: 出纳 | B10: 总账1001/1002科目；仅现金银行科目之间的凭证识别为内部划转。复合凭证仍需复核。
A11: 利润口径 | B11: 利润表本月balance、本年累计curBalance、上年累计preBalance；以账无忧报表为准。
A12: 现金流字段 | B12: 保留原接口字段名，字段期间口径需对照账套现金流量表；不将未知字段重命名。
A13: 异常 | B13: 失败时保留旧数据；更换选择但未刷新时统计页留空；原系统校验信息在刷新信息中。
A14: 参考结构 | B14: https://www.vertex42.com/ExcelTemplates/financial-statements.html
A15: 参考范围 | B15: https://www.smartsheet.com/content/free-business-templates
